Workbook

Sheet Inversión Inicial
A1: ESCENARIO BASE DOCUMENTAL: la Fase 1 se planifica en 165.000 € prudente / 180.000 € central / 195.000 € techo. No equivale a caja cobrada.
B2: Inversión Inicial
B4: Inmovilizado Material
B5: Concepto | C5: Adq. a Empresas (sin IVA) | D5: IVA 21% | E5: Adq. a Particulares (ITPYAJD) | F5: ITPYAJD | H5: Aportación en Especie | J5: TOTALES | K5: €
B6: Adquisición del terreno | C6: 0 | D6: =C6*0.21 -> 0 | E6: 0 | F6: 0.08 | G6: =E6*F6 -> 0 | H6: 0 | J6: Inmovilizado Material: | K6: =SUM(C6+C7+C8+C9+C10+C11+C12+C13+C14+C15+C16+E6+E7+E8+E9+E10+E11+E12+E13+E14+E15+E16+H6+H7+H8+H9+H10+H11+H12+H13+H14+H15+H16) -> 10000
B7: Edificios y Construcciones | C7: 0 | D7: =C7*0.21 -> 0 | E7: 0 | F7: 0.08 | G7: =E7*F7 -> 0 | H7: 0 | J7: Inmovilizado Inmaterial: | K7: =C19+C20+C21+C22+C23+C24+C25+E19+E20+E21+E22+E23+E24+E25+H19+H20+H21+H22+H23+H24+H25 -> 82460.72
B8: Instalaciones | C8: 0 | D8: =C8*0.21 -> 0 | E8: 0 | F8: 0.06 | G8: =E8*F8 -> 0 | H8: 0 | J8: Activo no Corriente Total: | K8: =K6+K7 -> 92460.72
B9: Maquinaria | C9: 0 | D9: =C9*0.21 -> 0 | E9: 0 | F9: 0.06 | G9: =E9*F9 -> 0 | H9: 0
B10: Equipamiento | C10: 0 | D10: =C10*0.21 -> 0 | E10: 0 | F10: 0.06 | G10: =E10*F10 -> 0 | H10: 0 | J10: Existencias Iniciales: | K10: =C28+E28+H28 -> 0
B11: Mobiliario | C11: 0 | D11: =C11*0.21 -> 0 | E11: 0 | F11: 0.06 | G11: =E11*F11 -> 0 | H11: 0 | J11: Tesorería inicial para puesta en marcha: | K11: =-('Necesidades de finaciación'!J19) -> 68166.78
B12: Utillaje | C12: 0 | D12: =C12*0.21 -> 0 | E12: 0 | F12: 0.06 | G12: =E12*F12 -> 0 | H12: 0 | J12: IVA Soportad Empresas | K12: =(D6+D7+D8+D9+D10+D11+D12+D13+D14+D15+D16+D19+D20+D21+D22+D23+D24+D25+D28) -> 19372.5
B13: Vehículos de transporte | C13: 0 | D13: =C13*0.21 -> 0 | E13: 0 | F13: 0.06 | G13: =E13*F13 -> 0 | H13: 0 | J13: ITPYAJD Soportado particulares | K13: =G6+G7+G8+G9+G10+G11+G12+G13+G14+G15+G16+G19+G20+G21+G22+G23+G24+G25+G28 -> 0
B14: Equipos informáticos | C14: 0 | D14: =C14*0.21 -> 0 | E14: 0 | F14: 0.06 | G14: =E14*F14 -> 0 | H14: 0 | J14: Activo Corriente Total: | K14: =K12+K13+K10+K11 -> 87539.28
B15: Equipos y medios técnicos F1 (escenario base) | C15: 10000 | D15: =C15*0.21 -> 2100 | E15: 0 | F15: 0.06 | G15: =E15*F15 -> 0 | H15: 0
B16: Fianza | C16: 0 | E16: 0 | F16: 0 | H16: 0 | J16: Necesidades Totales de Aportación en Especie | K16: =K8+K14 -> 180000
B17: Inmovilizado Inmaterial
B18: Concepto | C18: Adq. a Empresas (sin IVA) | D18: IVA 21% | E18: Adq. a Particulares (sin IVA) | F18: IVA | H18: Aportación en Especie
B19: I+D y validación técnica F1 (escenario base) | C19: 30000 | D19: =C19*0.21 -> 6300 | E19: 0 | F19: 0.06 | G19: =E19*F19 -> 0 | H19: 0
B20: Patentes, Modelos de Utilidad | C20: 0 | D20: =C20*0.21 -> 0 | E20: 0 | F20: 0.06 | G20: =E20*F20 -> 0 | H20: 0
B21: Aplicaciones informáticas F1 (escenario base) | C21: 47250 | D21: =C21*0.21 -> 9922.5 | E21: 0 | F21: 0.06 | G21: =E21*F21 -> 0 | H21: 0
B22: Derechos de traspaso, Concesiones administrativas, Tasas, Licencias... | C22: 0 | D22: 0 | E22: 0 | F22: 0 | G22: =E22*F22 -> 0 | H22: 0
B23: Marca, nombre comercial y tasas (documentado/en trámite) | C23: 210.72 | D23: 0 | E23: 0 | F23: 0 | G23: =E23*F23 -> 0 | H23: 0
B24: Legal, administración y contingencia F1 | C24: 5000 | D24: =C24*0.21 -> 1050 | E24: 0 | F24: 0.06 | G24: =E24*0.06 -> 0 | H24: 0
B25: Fondo de Comercio | C25: 0 | D25: 0 | E25: 0 | F25: 0 | G25: =E25*F25 -> 0 | H25: 0
B26: Activo Corriente
B27: Concepto | C27: Adq. a Empresas (sin IVA) | D27: IVA 21% | E27: Adq. a Particulares (sin IVA) | F27: IVA | H27: Aportación en Especie
B28: Existencias Iniciales (M.P., productos terminados, envases y embalajes) | C28: 0 | D28: =C28*0.21 -> 0 | E28: 0 | F28: 0.08 | G28: =E28*0.08 -> 0 | H28: 0

Sheet Pago de Inversiones
B3: Pago de Inversiones
B5: Concepto | C5: Importe Total | D5: % | E5: Mes 0 | F5: % | G5: Mes 1 | H5: % | I5: Mes 2 | J5: % | K5: Mes 3 | L5: % | M5: Mes 4 | N5: % | O5: Mes 5 | P5: % | Q5: Mes 6 | R5: % | S5: Mes 7 | T5: % | U5: Mes 8 | V5: % | W5: Mes 9 | X5: % | Y5: Mes 10 | Z5: % | AA5: Mes 11 | AB5: % | AC5: Mes 12 | AD5: Calculo correcto
B6: Adquisición del terreno | C6: ='Inversión Inicial'!C6+'Inversión Inicial'!D6+'Inversión Inicial'!E6+'Inversión Inicial'!G6 -> 0 | D6: 0 | E6: =(C6*D6) -> 0 | F6: 0 | G6: =C6*F6 -> 0 | H6: 0 | I6: =C6*H6 -> 0 | J6: 0 | K6: =C6*J6 -> 0 | L6: 0 | M6: =C6*L6 -> 0 | N6: 0 | O6: =C6*N6 -> 0 | P6: 0 | Q6: =C6*P6 -> 0 | R6: 0 | S6: =C6*R6 -> 0 | T6: 0 | U6: =C6*T6 -> 0 | V6: 0 | W6: =C6*V6 -> 0 | X6: 0 | Y6: =C6*X6 -> 0 | Z6: 0 | AA6: =C6*Z6 -> 0 | AB6: 0 | AC6: =C6*AB6 -> 0 | AD6: =E6+G6+I6+K6+M6+O6+Q6+S6+U6+W6+Y6+AA6+AC6-C6 -> 0
B7: Edificios y Construcciones | C7: ='Inversión Inicial'!C7+'Inversión Inicial'!D7+'Inversión Inicial'!E7+'Inversión Inicial'!G7 -> 0 | D7: 0 | E7: =(C7*D7) -> 0 | F7: 0 | G7: =C7*F7 -> 0 | H7: 0 | I7: =C7*H7 -> 0 | J7: 0 | K7: =C7*J7 -> 0 | L7: 0 | M7: =C7*L7 -> 0 | N7: 0 | O7: =C7*N7 -> 0 | P7: 0 | Q7: =C7*P7 -> 0 | R7: 0 | S7: =C7*R7 -> 0 | T7: 0 | U7: =C7*T7 -> 0 | V7: 0 | W7: =C7*V7 -> 0 | X7: 0 | Y7: =C7*X7 -> 0 | Z7: 0 | AA7: =C7*Z7 -> 0 | AB7: 0 | AC7: =C7*AB7 -> 0 | AD7: =E7+G7+I7+K7+M7+O7+Q7+S7+U7+W7+Y7+AA7+AC7-C7 -> 0
B8: Instalaciones | C8: ='Inversión Inicial'!C8+'Inversión Inicial'!D8+'Inversión Inicial'!E8+'Inversión Inicial'!G8 -> 0 | D8: 0 | E8: =(C8*D8) -> 0 | F8: 0 | G8: =C8*F8 -> 0 | H8: 0 | I8: =C8*H8 -> 0 | J8: 0 | K8: =C8*J8 -> 0 | L8: 0 | M8: =C8*L8 -> 0 | N8: 0 | O8: =C8*N8 -> 0 | P8: 0 | Q8: =C8*P8 -> 0 | R8: 0 | S8: =C8*R8 -> 0 | T8: 0 | U8: =C8*T8 -> 0 | V8: 0 | W8: =C8*V8 -> 0 | X8: 0 | Y8: =C8*X8 -> 0 | Z8: 0 | AA8: =C8*Z8 -> 0 | AB8: 0 | AC8: =C8*AB8 -> 0 | AD8: =E8+G8+I8+K8+M8+O8+Q8+S8+U8+W8+Y8+AA8+AC8-C8 -> 0
B9: Maquinaria | C9: ='Inversión Inicial'!C9+'Inversión Inicial'!D9+'Inversión Inicial'!E9+'Inversión Inicial'!G9 -> 0 | D9: 0 | E9: =(C9*D9) -> 0 | F9: 0 | G9: =C9*F9 -> 0 | H9: 0 | I9: =C9*H9 -> 0 | J9: 0 | K9: =C9*J9 -> 0 | L9: 0 | M9: =C9*L9 -> 0 | N9: 0 | O9: =C9*N9 -> 0 | P9: 0 | Q9: =C9*P9 -> 0 | R9: 0 | S9: =C9*R9 -> 0 | T9: 0 | U9: =C9*T9 -> 0 | V9: 0 | W9: =C9*V9 -> 0 | X9: 0 | Y9: =C9*X9 -> 0 | Z9: 0 | AA9: =C9*Z9 -> 0 | AB9: 0 | AC9: =C9*AB9 -> 0 | AD9: =E9+G9+I9+K9+M9+O9+Q9+S9+U9+W9+Y9+AA9+AC9-C9 -> 0
B10: Equipamiento | C10: ='Inversión Inicial'!C10+'Inversión Inicial'!D10+'Inversión Inicial'!E10+'Inversión Inicial'!G10 -> 0 | D10: 0 | E10: =(C10*D10) -> 0 | F10: 0 | G10: =C10*F10 -> 0 | H10: 0 | I10: =C10*H10 -> 0 | J10: 0 | K10: =C10*J10 -> 0 | L10: 0 | M10: =C10*L10 -> 0 | N10: 0 | O10: =C10*N10 -> 0 | P10: 0 | Q10: =C10*P10 -> 0 | R10: 0 | S10: =C10*R10 -> 0 | T10: 0 | U10: =C10*T10 -> 0 | V10: 0 | W10: =C10*V10 -> 0 | X10: 0 | Y10: =C10*X10 -> 0 | Z10: 0 | AA10: =C10*Z10 -> 0 | AB10: 0 | AC10: =C10*AB10 -> 0 | AD10: =E10+G10+I10+K10+M10+O10+Q10+S10+U10+W10+Y10+AA10+AC10-C10 -> 0
B11: Mobiliario | C11: ='Inversión Inicial'!C11+'Inversión Inicial'!D11+'Inversión Inicial'!E11+'Inversión Inicial'!G11 -> 0 | D11: 0 | E11: =(C11*D11) -> 0 | F11: 0 | G11: =C11*F11 -> 0 | H11: 0 | I11: =C11*H11 -> 0 | J11: 0 | K11: =C11*J11 -> 0 | L11: 0 | M11: =C11*L11 -> 0 | N11: 0 | O11: =C11*N11 -> 0 | P11: 0 | Q11: =C11*P11 -> 0 | R11: 0 | S11: =C11*R11 -> 0 | T11: 0 | U11: =C11*T11 -> 0 | V11: 0 | W11: =C11*V11 -> 0 | X11: 0 | Y11: =C11*X11 -> 0 | Z11: 0 | AA11: =C11*Z11 -> 0 | AB11: 0 | AC11: =C11*AB11 -> 0 | AD11: =E11+G11+I11+K11+M11+O11+Q11+S11+U11+W11+Y11+AA11+AC11-C11 -> 0
B12: Utillaje | C12: ='Inversión Inicial'!C12+'Inversión Inicial'!D12+'Inversión Inicial'!E12+'Inversión Inicial'!G12 -> 0 | D12: 0 | E12: =(C12*D12) -> 0 | F12: 0 | G12: =C12*F12 -> 0 | H12: 0 | I12: =C12*H12 -> 0 | J12: 0 | K12: =C12*J12 -> 0 | L12: 0 | M12: =C12*L12 -> 0 | N12: 0 | O12: =C12*N12 -> 0 | P12: 0 | Q12: =C12*P12 -> 0 | R12: 0 | S12: =C12*R12 -> 0 | T12: 0 | U12: =C12*T12 -> 0 | V12: 0 | W12: =C12*V12 -> 0 | X12: 0 | Y12: =C12*X12 -> 0 | Z12: 0 | AA12: =C12*Z12 -> 0 | AB12: 0 | AC12: =C12*AB12 -> 0 | AD12: =E12+G12+I12+K12+M12+O12+Q12+S12+U12+W12+Y12+AA12+AC12-C12 -> 0
B13: Vehículos de transporte | C13: ='Inversión Inicial'!C13+'Inversión Inicial'!D13+'Inversión Inicial'!E13+'Inversión Inicial'!G13 -> 0 | D13: 0 | E13: =(C13*D13) -> 0 | F13: 0 | G13: =C13*F13 -> 0 | H13: 0 | I13: =C13*H13 -> 0 | J13: 0 | K13: =C13*J13 -> 0 | L13: 0 | M13: =C13*L13 -> 0 | N13: 0 | O13: =C13*N13 -> 0 | P13: 0 | Q13: =C13*P13 -> 0 | R13: 0 | S13: =C13*R13 -> 0 | T13: 0 | U13: =C13*T13 -> 0 | V13: 0 | W13: =C13*V13 -> 0 | X13: 0 | Y13: =C13*X13 -> 0 | Z13: 0 | AA13: =C13*Z13 -> 0 | AB13: 0 | AC13: =C13*AB13 -> 0 | AD13: =E13+G13+I13+K13+M13+O13+Q13+S13+U13+W13+Y13+AA13+AC13-C13 -> 0
B14: Equipos informáticos | C14: ='Inversión Inicial'!C14+'Inversión Inicial'!D14+'Inversión Inicial'!E14+'Inversión Inicial'!G14 -> 0 | D14: 0 | E14: =(C14*D14) -> 0 | F14: 0 | G14: =C14*F14 -> 0 | H14: 0 | I14: =C14*H14 -> 0 | J14: 0 | K14: =C14*J14 -> 0 | L14: 0 | M14: =C14*L14 -> 0 | N14: 0 | O14: =C14*N14 -> 0 | P14: 0 | Q14: =C14*P14 -> 0 | R14: 0 | S14: =C14*R14 -> 0 | T14: 0 | U14: =C14*T14 -> 0 | V14: 0 | W14: =C14*V14 -> 0 | X14: 0 | Y14: =C14*X14 -> 0 | Z14: 0 | AA14: =C14*Z14 -> 0 | AB14: 0 | AC14: =C14*AB14 -> 0 | AD14: =E14+G14+I14+K14+M14+O14+Q14+S14+U14+W14+Y14+AA14+AC14-C14 -> 0
B15: Otros (proyectos técnicos...) | C15: ='Inversión Inicial'!C15+'Inversión Inicial'!D15+'Inversión Inicial'!E15+'Inversión Inicial'!G15 -> 12100 | D15: 0 | E15: =(C15*D15) -> 0 | F15: 0 | G15: =C15*F15 -> 0 | H15: 0 | I15: =C15*H15 -> 0 | J15: 0 | K15: =C15*J15 -> 0 | L15: 0 | M15: =C15*L15 -> 0 | N15: 0 | O15: =C15*N15 -> 0 | P15: 0 | Q15: =C15*P15 -> 0 | R15: 0 | S15: =C15*R15 -> 0 | T15: 0 | U15: =C15*T15 -> 0 | V15: 0 | W15: =C15*V15 -> 0 | X15: 0 | Y15: =C15*X15 -> 0 | Z15: 0 | AA15: =C15*Z15 -> 0 | AB15: 0 | AC15: =C15*AB15 -> 0 | AD15: =E15+G15+I15+K15+M15+O15+Q15+S15+U15+W15+Y15+AA15+AC15-C15 -> -12100
B16: Gastos de I+D | C16: ='Inversión Inicial'!C19+'Inversión Inicial'!D19+'Inversión Inicial'!E19+'Inversión Inicial'!G19 -> 36300 | D16: 0 | E16: =(C16*D16) -> 0 | F16: 0 | G16: =C16*F16 -> 0 | H16: 0 | I16: =C16*H16 -> 0 | J16: 0 | K16: =C16*J16 -> 0 | L16: 0 | M16: =C16*L16 -> 0 | N16: 0 | O16: =C16*N16 -> 0 | P16: 0 | Q16: =C16*P16 -> 0 | R16: 0 | S16: =C16*R16 -> 0 | T16: 0 | U16: =C16*T16 -> 0 | V16: 0 | W16: =C16*V16 -> 0 | X16: 0 | Y16: =C16*X16 -> 0 | Z16: 0 | AA16: =C16*Z16 -> 0 | AB16: 0 | AC16: =C16*AB16 -> 0 | AD16: =E16+G16+I16+K16+M16+O16+Q16+S16+U16+W16+Y16+AA16+AC16-C16 -> -36300
B17: Patentes, Modelos de Utilidad | C17: ='Inversión Inicial'!C20+'Inversión Inicial'!D20+'Inversión Inicial'!E20+'Inversión Inicial'!G20 -> 0 | D17: 0 | E17: =(C17*D17) -> 0 | F17: 0 | G17: =C17*F17 -> 0 | H17: 0 | I17: =C17*H17 -> 0 | J17: 0 | K17: =C17*J17 -> 0 | L17: 0 | M17: =C17*L17 -> 0 | N17: 0 | O17: =C17*N17 -> 0 | P17: 0 | Q17: =C17*P17 -> 0 | R17: 0 | S17: =C17*R17 -> 0 | T17: 0 | U17: =C17*T17 -> 0 | V17: 0 | W17: =C17*V17 -> 0 | X17: 0 | Y17: =C17*X17 -> 0 | Z17: 0 | AA17: =C17*Z17 -> 0 | AB17: 0 | AC17: =C17*AB17 -> 0 | AD17: =E17+G17+I17+K17+M17+O17+Q17+S17+U17+W17+Y17+AA17+AC17-C17 -> 0
B18: Aplicaciones informáticas | C18: ='Inversión Inicial'!C21+'Inversión Inicial'!D21+'Inversión Inicial'!E21+'Inversión Inicial'!G21 -> 57172.5 | D18: 0 | E18: =(C18*D18) -> 0 | F18: 0 | G18: =C18*F18 -> 0 | H18: 0 | I18: =C18*H18 -> 0 | J18: 0 | K18: =C18*J18 -> 0 | L18: 0 | M18: =C18*L18 -> 0 | N18: 0 | O18: =C18*N18 -> 0 | P18: 0 | Q18: =C18*P18 -> 0 | R18: 0 | S18: =C18*R18 -> 0 | T18: 0 | U18: =C18*T18 -> 0 | V18: 0 | W18: =C18*V18 -> 0 | X18: 0 | Y18: =C18*X18 -> 0 | Z18: 0 | AA18: =C18*Z18 -> 0 | AB18: 0 | AC18: =C18*AB18 -> 0 | AD18: =E18+G18+I18+K18+M18+O18+Q18+S18+U18+W18+Y18+AA18+AC18-C18 -> -57172.5
B19: Derechos de traspaso, Concesiones administrativas, Tasas, Licencias... | C19: ='Inversión Inicial'!C22+'Inversión Inicial'!E22+'Inversión Inicial'!G22 -> 0 | D19: 0 | E19: =(C19*D19) -> 0 | F19: 0 | G19: =C19*F19 -> 0 | H19: 0 | I19: =C19*H19 -> 0 | J19: 0 | K19: =C19*J19 -> 0 | L19: 0 | M19: =C19*L19 -> 0 | N19: 0 | O19: =C19*N19 -> 0 | P19: 0 | Q19: =C19*P19 -> 0 | R19: 0 | S19: =C19*R19 -> 0 | T19: 0 | U19: =C19*T19 -> 0 | V19: 0 | W19: =C19*V19 -> 0 | X19: 0 | Y19: =C19*X19 -> 0 | Z19: 0 | AA19: =C19*Z19 -> 0 | AB19: 0 | AC19: =C19*AB19 -> 0 | AD19: =E19+G19+I19+K19+M19+O19+Q19+S19+U19+W19+Y19+AA19+AC19-C19 -> 0
B20: Marca, Nombre Comercial | C20: ='Inversión Inicial'!C23+'Inversión Inicial'!E23+'Inversión Inicial'!G23 -> 210.72 | D20: 0 | E20: =(C20*D20) -> 0 | F20: 0 | G20: =C20*F20 -> 0 | H20: 0 | I20: =C20*H20 -> 0 | J20: 0 | K20: =C20*J20 -> 0 | L20: 0 | M20: =C20*L20 -> 0 | N20: 0 | O20: =C20*N20 -> 0 | P20: 0 | Q20: =C20*P20 -> 0 | R20: 0 | S20: =C20*R20 -> 0 | T20: 0 | U20: =C20*T20 -> 0 | V20: 0 | W20: =C20*V20 -> 0 | X20: 0 | Y20: =C20*X20 -> 0 | Z20: 0 | AA20: =C20*Z20 -> 0 | AB20: 0 | AC20: =C20*AB20 -> 0 | AD20: =E20+G20+I20+K20+M20+O20+Q20+S20+U20+W20+Y20+AA20+AC20-C20 -> -210.72
B21: Otros (...) | C21: ='Inversión Inicial'!C24+'Inversión Inicial'!D24+'Inversión Inicial'!E24+'Inversión Inicial'!G24 -> 6050 | D21: 0 | E21: =(C21*D21) -> 0 | F21: 0 | G21: =C21*F21 -> 0 | H21: 0 | I21: =C21*H21 -> 0 | J21: 0 | K21: =C21*J21 -> 0 | L21: 0 | M21: =C21*L21 -> 0 | N21: 0 | O21: =C21*N21 -> 0 | P21: 0 | Q21: =C21*P21 -> 0 | R21: 0 | S21: =C21*R21 -> 0 | T21: 0 | U21: =C21*T21 -> 0 | V21: 0 | W21: =C21*V21 -> 0 | X21: 0 | Y21: =C21*X21 -> 0 | Z21: 0 | AA21: =C21*Z21 -> 0 | AB21: 0 | AC21: =C21*AB21 -> 0 | AD21: =E21+G21+I21+K21+M21+O21+Q21+S21+U21+W21+Y21+AA21+AC21-C21 -> -6050
B22: Fondo de Comercio | C22: ='Inversión Inicial'!C25+'Inversión Inicial'!E25 -> 0 | D22: 0 | E22: =(C22*D22) -> 0 | F22: 0 | G22: =C22*F22 -> 0 | H22: 0 | I22: =C22*H22 -> 0 | J22: 0 | K22: =C22*J22 -> 0 | L22: 0 | M22: =C22*L22 -> 0 | N22: 0 | O22: =C22*N22 -> 0 | P22: 0 | Q22: =C22*P22 -> 0 | R22: 0 | S22: =C22*R22 -> 0 | T22: 0 | U22: =C22*T22 -> 0 | V22: 0 | W22: =C22*V22 -> 0 | X22: 0 | Y22: =C22*X22 -> 0 | Z22: 0 | AA22: =C22*Z22 -> 0 | AB22: 0 | AC22: =C22*AB22 -> 0 | AD22: =E22+G22+I22+K22+M22+O22+Q22+S22+U22+W22+Y22+AA22+AC22-C22 -> 0
B23: Existencias Iniciales (M.P., productos terminados, envases y embalajes) | C23: ='Inversión Inicial'!C28+'Inversión Inicial'!D28+'Inversión Inicial'!E28+'Inversión Inicial'!G28 -> 0 | D23: 0 | E23: =(C23*D23) -> 0 | F23: 0 | G23: =C23*F23 -> 0 | H23: 0 | I23: =C23*H23 -> 0 | J23: 0 | K23: =C23*J23 -> 0 | L23: 0 | M23: =C23*L23 -> 0 | N23: 0 | O23: =C23*N23 -> 0 | P23: 0 | Q23: =C23*P23 -> 0 | R23: 0 | S23: =C23*R23 -> 0 | T23: 0 | U23: =C23*T23 -> 0 | V23: 0 | W23: =C23*V23 -> 0 | X23: 0 | Y23: =C23*X23 -> 0 | Z23: 0 | AA23: =C23*Z23 -> 0 | AB23: 0 | AC23: =C23*AB23 -> 0 | AD23: =E23+G23+I23+K23+M23+O23+Q23+S23+U23+W23+Y23+AA23+AC23-C23 -> 0
B24: Fianza | C24: ='Inversión Inicial'!C16+'Inversión Inicial'!D16+'Inversión Inicial'!E16+'Inversión Inicial'!G16 -> 0 | D24: 0 | E24: =(C24*D24) -> 0 | F24: 0 | G24: =C24*F24 -> 0 | H24: 0 | I24: =C24*H24 -> 0 | J24: 0 | K24: =C24*J24 -> 0 | L24: 0 | M24: =C24*L24 -> 0 | N24: 0 | O24: =C24*N24 -> 0 | P24: 0 | Q24: =C24*P24 -> 0 | R24: 0 | S24: =C24*R24 -> 0 | T24: 0 | U24: =C24*T24 -> 0 | V24: 0 | W24: =C24*V24 -> 0 | X24: 0 | Y24: =C24*X24 -> 0 | Z24: 0 | AA24: =C24*Z24 -> 0 | AB24: 0 | AC24: =C24*AB24 -> 0 | AD24: =E24+G24+I24+K24+M24+O24+Q24+S24+U24+W24+Y24+AA24+AC24-C24 -> 0
B25: TOTALES | C25: =SUM(C6:C24) -> 111833.22 | E25: =SUM(E6:E24) -> 0 | G25: =SUM(G6:G24) -> 0 | I25: =SUM(I6:I24) -> 0 | K25: =SUM(K6:K24) -> 0 | M25: =SUM(M6:M24) -> 0 | O25: =SUM(O6:O24) -> 0 | Q25: =SUM(Q6:Q24) -> 0 | S25: =SUM(S6:S24) -> 0 | U25: =SUM(U6:U24) -> 0 | W25: =SUM(W6:W24) -> 0 | Y25: =SUM(Y6:Y24) -> 0 | AA25: =SUM(AA6:AA24) -> 0 | AC25: =SUM(AC6:AC24) -> 0 | AD25: =E25+G25+I25+K25+M25+O25+Q25+S25+U25+W25+Y25+AA25+AC25-C25 -> -111833.22
B27: Sólo tienes que completar el % que vas a imputar a cada mes, el resto se calcula de manera automática.

Sheet Necesidades de finaciación
A1: ESCENARIO PROFORMA — NO ES FINANCIACIÓN CONCEDIDA NI COBRADA
A2: La financiación cobrada y la caja propia inicial son ambas 0,00 €. El Excel reproduce únicamente un escenario condicionado a formalización y desembolso.
B3: Necesidades de Financiación
B6: Recursos Propios
I7: TOTALES | J7: €
B8: Concepto | F8: Importe | I8: Aportaciones en especies | J8: ='Inversión Inicial'!H6+'Inversión Inicial'!H7+'Inversión Inicial'!H8+'Inversión Inicial'!H9+'Inversión Inicial'!H10+'Inversión Inicial'!H11+'Inversión Inicial'!H12+'Inversión Inicial'!H13+'Inversión Inicial'!H14+'Inversión Inicial'!H15+'Inversión Inicial'!H16+'Inversión Inicial'!H19+'Inversión Inicial'!H20+'Inversión Inicial'!H21+'Inversión Inicial'!H22+'Inversión Inicial'!H23+'Inversión Inicial'!H24+'Inversión Inicial'!H25+'Inversión Inicial'!H28 -> 0
B9: Aportaciones Dinerarias | F9: 0 | I9: Aportaciones de socios total: | J9: =F9+J8 -> 0
B10: Otros (pago único desempleado, subvenciones cobradas, …) | F10: 0 | I10: Recursos propios: | J10: =F9+F10+J8 -> 0
I12: Deudas Bancarias | J12: =F17+F18 -> 180000
B13: Recursos Ajenos a Largo Plazo | I13: Recursos Ajenos a L/P | J13: =F16+J12 -> 180000
B15: Concepto | F15: Importe | G15: Años | H15: Tipo de interés nominal anual | I15: Proveedores Varios C/P | J15: ='Pago de Inversiones'!G25+'Pago de Inversiones'!I25+'Pago de Inversiones'!K25+'Pago de Inversiones'!M25+'Pago de Inversiones'!O25+'Pago de Inversiones'!Q25+'Pago de Inversiones'!S25+'Pago de Inversiones'!U25+'Pago de Inversiones'!W25+'Pago de Inversiones'!Y25+'Pago de Inversiones'!AA25+'Pago de Inversiones'!AC25+F24 -> 0
B16: Otras deudas a largo plazo | F16: 0
B17: Financiación externa central F1 — pendiente de formalización y desembolso | F17: 180000 | G17: 7 | H17: 0.07 | I17: Pasivo Total | J17: =J10+J15+J13 -> 180000
B18: Microcrédito | F18: 0 | G18: 0 | H18: 0
I19: ='Inversión Inicial'!J16 -> Necesidades Totales de Aportación en Especie | J19: =('Inversión Inicial'!K8+'Inversión Inicial'!K10+'Inversión Inicial'!K12+'Inversión Inicial'!K13)-J17 -> -68166.78
B21: Recursos Ajenos a Corto Plazo
B23: Concepto | F23: Importe | H23: Tipo de interés nominal anual
B24: Deudas a Corto Plazo | F24: 0 | H24: 0
A25: Liquidez: caja propia inicial 0 €. La financiación externa central de 180.000 € requiere póliza/préstamo de emprendimiento o desembolso documentado. El flujo oficial solo la simula en escenario proforma condicionado.

Sheet Costes produción y ventas
B2: COSTES DE PRODUCIÓN
B3: Producto | C3: Precio/unid | D3: % IVA | E3: Sub/Total/unid | F3: Total unidades año | G3: Total € anual (IVA incl)
A4: soportado | B4: SaaS agro-energético y cuaderno digital | C4: 65 | D4: 0.21 | E4: =C4*D4+C4 -> 78.65 | F4: 72 | G4: =E4*F4 -> 5662.8
B5: Implantación y parametrización | C5: 300 | D5: 0.21 | E5: =C5*D5+C5 -> 363 | F5: 5 | G5: =E5*F5 -> 1815
B6: Formación y acompañamiento | C6: 150 | D6: 0.21 | E6: =C6*D6+C6 -> 181.5 | F6: 9 | G6: =E6*F6 -> 1633.5
B7: Kit sensórico e integración de campo | C7: 400 | D7: 0.21 | E7: =C7*D7+C7 -> 484 | F7: 5 | G7: =E7*F7 -> 2420
B8: Consultoría y evidencias | C8: 391.5 | D8: 0.21 | E8: =C8*D8+C8 -> 473.715 | F8: 3 | G8: =E8*F8 -> 1421.145
B11: INGRESOS POR VENTA
B12: Producto | C12: Precio/unid | D12: % IVA | E12: Sub/Total/unid | F12: Total unidades año | G12: Total € anual (IVA incl)
A13: repercutido | B13: =B4 -> SaaS agro-energético y cuaderno digital | C13: 250 | D13: 0.21 | E13: =C13*D13+C13 -> 302.5 | F13: =F4 -> 72 | G13: =E13*F13 -> 21780
B14: =B5 -> Implantación y parametrización | C14: 1500 | D14: 0.21 | E14: =C14*D14+C14 -> 1815 | F14: =F5 -> 5 | G14: =E14*F14 -> 9075
B15: =B6 -> Formación y acompañamiento | C15: 500 | D15: 0.21 | E15: =C15*D15+C15 -> 605 | F15: =F6 -> 9 | G15: =E15*F15 -> 5445
B16: =B7 -> Kit sensórico e integración de campo | C16: 1200 | D16: 0.21 | E16: =C16*D16+C16 -> 1452 | F16: =F7 -> 5 | G16: =E16*F16 -> 7260
B17: =B8 -> Consultoría y evidencias | C17: 1166.6667 | D17: 0.21 | E17: =C17*D17+C17 -> 1411.6667 | F17: =F8 -> 3 | G17: =E17*F17 -> 4235
G19: INGRESOS POR VENTAS ANUALES
D20: =B4 -> SaaS agro-energético y cuaderno digital | G20: TOTAL | H20: Mes 1 | I20: Mes 2 | J20: Mes 3 | K20: Mes 4 | L20: Mes 5 | M20: Mes 6 | N20: Mes 7 | O20: Mes 8 | P20: Mes 9 | Q20: Mes 10 | R20: Mes 11 | S20: Mes 12 | T20: Salir exacto
D21: Nº Productos/Servicios | G21: =F4 -> 72 | H21: 0 | I21: 0 | J21: 2 | K21: 3 | L21: 4 | M21: 5 | N21: 6 | O21: 7 | P21: 8 | Q21: 9 | R21: 13 | S21: 15 | T21: =G21-H21-I21-J21-K21-L21-M21-N21-O21-P21-Q21-R21-S21 -> 0
D22: Precio de venta | G22: =C13 -> 250 | H22: =G22 -> 250 | I22: =G22 -> 250 | J22: =G22 -> 250 | K22: =G22 -> 250 | L22: =G22 -> 250 | M22: =G22 -> 250 | N22: =G22 -> 250 | O22: =G22 -> 250 | P22: =G22 -> 250 | Q22: =G22 -> 250 | R22: =G22 -> 250 | S22: =G22 -> 250
D23: Ingresos ventas | G23: =G21*G22 -> 18000 | H23: =H21*H22 -> 0 | I23: =I21*I22 -> 0 | J23: =J21*J22 -> 500 | K23: =K21*K22 -> 750 | L23: =L21*L22 -> 1000 | M23: =M21*M22 -> 1250 | N23: =N21*N22 -> 1500 | ... S23: =S21*S22 -> 3750 | T23: =G23-H23-I23-J23-K23-L23-M23-N23-O23-P23-Q23-R23-S23 -> 0
D24: Costes producción | G24: =C4*F4 -> 4680 | H24: =H21*C4 -> 0 | I24: =I21*C4 -> 0 | J24: =J21*C4 -> 130 | K24: =K21*C4 -> 195 | L24: =L21*C4 -> 260 | M24: =M21*C4 -> 325 | N24: =N21*C4 -> 390 | O24: =O21*C4 -> 455 | P24: =P21*C4 -> 520 | Q24: =Q21*C4 -> 585 | R24: =R21*C4 -> 845 | S24: =S21*C4 -> 975 | T24: =G24-H24-I24-J24-K24-L24-M24-N24-O24-P24-Q24-R24-S24 -> 0
D25: Margen Bruto | G25: =G23-G24 -> 13320 | H25: =H23-H24 -> 0 | I25: =I23-I24 -> 0 | J25: =J23-J24 -> 370 | K25: =K23-K24 -> 555 | L25: =L23-L24 -> 740 | M25: =M23-M24 -> 925 | N25: =N23-N24 -> 1110 | ... S25: =S23-S24 -> 2775 | T25: =G25-H25-I25-J25-K25-L25-M25-N25-O25-P25-Q25-R25-S25 -> 0
G27: INGRESOS POR VENTAS ANUALES
D28: =B5 -> Implantación y parametrización | G28: TOTAL | H28: Mes 1 | I28: Mes 2 | J28: Mes 3 | K28: Mes 4 | L28: Mes 5 | M28: Mes 6 | N28: Mes 7 | O28: Mes 8 | P28: Mes 9 | Q28: Mes 10 | R28: Mes 11 | S28: Mes 12 | T28: Salir exacto
D29: Nº Productos/Servicios | G29: =F5 -> 5 | H29: 0 | I29: 0 | J29: 0 | K29: 0 | L29: 0 | M29: 1 | N29: 1 | O29: 1 | P29: 1 | Q29: 1 | R29: 0 | S29: 0 | T29: =G29-H29-I29-J29-K29-L29-M29-N29-O29-P29-Q29-R29-S29 -> 0
D30: Precio de venta | G30: =C14 -> 1500 | H30: =G30 -> 1500 | I30: =G30 -> 1500 | J30: =G30 -> 1500 | K30: =G30 -> 1500 | L30: =G30 -> 1500 | M30: =G30 -> 1500 | N30: =G30 -> 1500 | O30: =G30 -> 1500 | P30: =G30 -> 1500 | Q30: =G30 -> 1500 | R30: =G30 -> 1500 | S30: =G30 -> 1500
D31: Ingresos ventas | G31: =G29*G30 -> 7500 | H31: =H29*H30 -> 0 | I31: =I29*I30 -> 0 | J31: =J29*J30 -> 0 | K31: =K29*K30 -> 0 | L31: =L29*L30 -> 0 | M31: =M29*M30 -> 1500 | N31: =N29*N30 -> 1500 | ... S31: =S29*S30 -> 0 | T31: =G31-H31-I31-J31-K31-L31-M31-N31-O31-P31-Q31-R31-S31 -> 0
D32: Costes producción | G32: =F5*C5 -> 1500 | H32: =H29*C5 -> 0 | I32: =I29*C5 -> 0 | J32: =C5*J29 -> 0 | K32: =K29*C5 -> 0 | L32: =L29*C5 -> 0 | M32: =M29*C5 -> 300 | N32: =N29*C5 -> 300 | O32: =O29*C5 -> 300 | P32: =P29*C5 -> 300 | Q32: =Q29*C5 -> 300 | R32: =R29*C5 -> 0 | S32: =S29*C5 -> 0 | T32: =G32-H32-I32-J32-K32-L32-M32-N32-O32-P32-Q32-R32-S32 -> 0
D33: Margen Bruto | G33: =G31-G32 -> 6000 | H33: =H31-H32 -> 0 | I33: =I31-I32 -> 0 | J33: =J31-J32 -> 0 | K33: =K31-K32 -> 0 | L33: =L31-L32 -> 0 | M33: =M31-M32 -> 1200 | N33: =N31-N32 -> 1200 | ... S33: =S31-S32 -> 0 | T33: =G33-H33-I33-J33-K33-L33-M33-N33-O33-P33-Q33-R33-S33 -> 0
G35: INGRESOS POR VENTAS ANUALES
D36: =B6 -> Formación y acompañamiento | G36: TOTAL | H36: Mes 1 | I36: Mes 2 | J36: Mes 3 | K36: Mes 4 | L36: Mes 5 | M36: Mes 6 | N36: Mes 7 | O36: Mes 8 | P36: Mes 9 | Q36: Mes 10 | R36: Mes 11 | S36: Mes 12 | T36: Salir exacto
D37: Nº Productos/Servicios | G37: =F6 -> 9 | H37: 0 | I37: 0 | J37: 0 | K37: 1 | L37: 1 | M37: 1 | N37: 1 | O37: 1 | P37: 1 | Q37: 1 | R37: 1 | S37: 1 | T37: =G37-H37-I37-J37-K37-L37-M37-N37-O37-P37-Q37-R37-S37 -> 0
D38: Precio de venta | G38: =C15 -> 500 | H38: =G38 -> 500 | I38: =G38 -> 500 | J38: =G38 -> 500 | K38: =G38 -> 500 | L38: =G38 -> 500 | M38: =G38 -> 500 | N38: =G38 -> 500 | O38: =G38 -> 500 | P38: =G38 -> 500 | Q38: =G38 -> 500 | R38: =G38 -> 500 | S38: =G38 -> 500
D39: Ingresos ventas | G39: =G37*G38 -> 4500 | H39: =H37*H38 -> 0 | I39: =I37*I38 -> 0 | J39: =J37*J38 -> 0 | K39: =K37*K38 -> 500 | L39: =L37*L38 -> 500 | M39: =M37*M38 -> 500 | N39: =N37*N38 -> 500 | ... S39: =S37*S38 -> 500 | T39: =G39-H39-I39-J39-K39-L39-M39-N39-O39-P39-Q39-R39-S39 -> 0
D40: Costes producción | G40: =C6*F6 -> 1350 | H40: =H37*C6 -> 0 | I40: =I37*C6 -> 0 | J40: =J37*C6 -> 0 | K40: =K37*C6 -> 150 | L40: =L37*C6 -> 150 | M40: =M37*C6 -> 150 | N40: =N37*C6 -> 150 | O40: =O37*C6 -> 150 | P40: =P37*C6 -> 150 | Q40: =Q37*C6 -> 150 | R40: =R37*C6 -> 150 | S40: =S37*C6 -> 150 | T40: =G40-H40-I40-J40-K40-L40-M40-N40-O40-P40-Q40-R40-S40 -> 0
D41: Margen Bruto | G41: =G39-G40 -> 3150 | H41: =H39-H40 -> 0 | I41: =I39-I40 -> 0 | J41: =J39-J40 -> 0 | K41: =K39-K40 -> 350 | L41: =L39-L40 -> 350 | M41: =M39-M40 -> 350 | N41: =N39-N40 -> 350 | ... S41: =S39-S40 -> 350 | T41: =G41-H41-I41-J41-K41-L41-M41-N41-O41-P41-Q41-R41-S41 -> 0
G43: INGRESOS POR VENTAS ANUALES
D44: =B7 -> Kit sensórico e integración de campo | G44: TOTAL | H44: Mes 1 | I44: Mes 2 | J44: Mes 3 | K44: Mes 4 | L44: Mes 5 | M44: Mes 6 | N44: Mes 7 | O44: Mes 8 | P44: Mes 9 | Q44: Mes 10 | R44: Mes 11 | S44: Mes 12 | T44: Salir exacto
D45: Nº Productos/Servicios | G45: =F7 -> 5 | H45: 0 | I45: 0 | J45: 0 | K45: 0 | L45: 0 | M45: 0 | N45: 1 | O45: 1 | P45: 1 | Q45: 1 | R45: 1 | S45: 0 | T45: =G45-H45-I45-J45-K45-L45-M45-N45-O45-P45-Q45-R45-S45 -> 0
D46: Precio de venta | G46: =C16 -> 1200 | H46: =G46 -> 1200 | I46: =G46 -> 1200 | J46: =G46 -> 1200 | K46: =G46 -> 1200 | L46: =G46 -> 1200 | M46: =G46 -> 1200 | N46: =G46 -> 1200 | O46: =G46 -> 1200 | P46: =G46 -> 1200 | Q46: =G46 -> 1200 | R46: =G46 -> 1200 | S46: =G46 -> 1200
D47: Ingresos ventas | G47: =G45*G46 -> 6000 | H47: =H45*H46 -> 0 | I47: =I45*I46 -> 0 | J47: =J45*J46 -> 0 | K47: =K45*K46 -> 0 | L47: =L45*L46 -> 0 | M47: =M45*M46 -> 0 | N47: =N45*N46 -> 1200 | ... S47: =S45*S46 -> 0 | T47: =G47-H47-I47-J47-K47-L47-M47-N47-O47-P47-Q47-R47-S47 -> 0
D48: Costes producción | G48: =C7*F7 -> 2000 | H48: =H45*C7 -> 0 | I48: =I45*C7 -> 0 | J48: =J45*C7 -> 0 | K48: =K45*C7 -> 0 | L48: =L45*C7 -> 0 | M48: =M45*C7 -> 0 | N48: =N45*C7 -> 400 | O48: =O45*C7 -> 400 | P48: =P45*C7 -> 400 | Q48: =Q45*C7 -> 400 | R48: =R45*C7 -> 400 | S48: =S45*C7 -> 0 | T48: =G48-H48-I48-J48-K48-L48-M48-N48-O48-P48-Q48-R48-S48 -> 0
D49: Margen Bruto | G49: =G47-G48 -> 4000 | H49: =H47-H48 -> 0 | I49: =I47-I48 -> 0 | J49: =J47-J48 -> 0 | K49: =K47-K48 -> 0 | L49: =L47-L48 -> 0 | M49: =M47-M48 -> 0 | N49: =N47-N48 -> 800 | ... S49: =S47-S48 -> 0 | T49: =G49-H49-I49-J49-K49-L49-M49-N49-O49-P49-Q49-R49-S49 -> 0
G51: INGRESOS POR VENTAS ANUALES
D52: =B8 -> Consultoría y evidencias | G52: TOTAL | H52: Mes 1 | I52: Mes 2 | J52: Mes 3 | K52: Mes 4 | L52: Mes 5 | M52: Mes 6 | N52: Mes 7 | O52: Mes 8 | P52: Mes 9 | Q52: Mes 10 | R52: Mes 11 | S52: Mes 12 | T52: Salir exacto
D53: Nº Productos/Servicios | G53: =F8 -> 3 | H53: 0 | I53: 0 | J53: 0 | K53: 0 | L53: 0 | M53: 0 | N53: 0 | O53: 1 | P53: 1 | Q53: 1 | R53: 0 | S53: 0 | T53: =G53-H53-I53-J53-K53-L53-M53-N53-O53-P53-Q53-R53-S53 -> 0
D54: Precio de venta | G54: =C17 -> 1166.6667 | H54: =G54 -> 1166.6667 | I54: =G54 -> 1166.6667 | J54: =G54 -> 1166.6667 | K54: =G54 -> 1166.6667 | L54: =G54 -> 1166.6667 | M54: =G54 -> 1166.6667 | N54: =G54 -> 1166.6667 | O54: =G54 -> 1166.6667 | P54: =G54 -> 1166.6667 | Q54: =G54 -> 1166.6667 | R54: =G54 -> 1166.6667 | S54: =G54 -> 1166.6667
D55: Ingresos ventas | G55: =G53*G54 -> 3500 | H55: =H53*H54 -> 0 | I55: =I53*I54 -> 0 | J55: =J53*J54 -> 0 | K55: =K53*K54 -> 0 | L55: =L53*L54 -> 0 | M55: =M53*M54 -> 0 | N55: =N53*N54 -> 0 | ... S55: =S53*S54 -> 0 | T55: =G55-H55-I55-J55-K55-L55-M55-N55-O55-P55-Q55-R55-S55 -> 0
D56: Costes producción | G56: =C8*F8 -> 1174.5 | H56: =H53*C8 -> 0 | I56: =I53*C8 -> 0 | J56: =J53*C8 -> 0 | K56: =K53*C8 -> 0 | L56: =L53*C8 -> 0 | M56: =M53*C8 -> 0 | N56: =N53*C8 -> 0 | O56: =O53*C8 -> 391.5 | P56: =P53*C8 -> 391.5 | Q56: =Q53*C8 -> 391.5 | R56: =R53*C8 -> 0 | S56: =S53*C8 -> 0 | T56: =G56-H56-I56-J56-K56-L56-M56-N56-O56-P56-Q56-R56-S56 -> 0
D57: Margen Bruto | G57: =G55-G56 -> 2325.5 | H57: =H55-H56 -> 0 | I57: =I55-I56 -> 0 | J57: =J55-J56 -> 0 | K57: =K55-K56 -> 0 | L57: =L55-L56 -> 0 | M57: =M55-M56 -> 0 | N57: =N55-N56 -> 0 | ... S57: =S55-S56 -> 0 | T57: =G57-H57-I57-J57-K57-L57-M57-N57-O57-P57-Q57-R57-S57 -> 0
E59: Sin IVA
B60: INGRESOS POR VENTAS (AÑO 1, SIN IVA) | E60: =SUM(G23,G31,G39,G47,G55) -> 39500
B61: COSTES DIRECTOS (AÑO 1, SIN IVA) | E61: =SUM(G24,G32,G40,G48,G56) -> 10704.5
B62: MARGEN BRUTO | E62: =E60-E61 -> 28795.5
B63: MARGEN BRUTO SOBRE VENTAS | E63: =IFERROR(E62/E60,0) -> 0.729
A64: Costes directos incluyen consumibles sensóricos, licencias/cloud de terceros, mantenimiento de campo, pasarela y soporte operativo. En el escenario base representan el 27,1 % de las ventas y dejan margen bruto del 72,9 %.

Sheet Liquidación de IVA
B3: Liquidación de IVA
B5: 1º TRIMESTRE | H5: TOTALES | I5: €
C6: MES 1 | D6: MES 2 | E6: MES 3 | H6: Total IVA Soportado | I6: =C8+D8+E8+C14+D14+E14+C20+D20+E20+C26+D26+E26 -> 24430.945
B7: Repercutido | C7: =(('Costes produción y ventas'!E13-'Costes produción y ventas'!C13)*'Costes produción y ventas'!H21)+(('Costes produción y ventas'!E14-'Costes produción y ventas'!C14)*'Costes produción y ventas'!H29)+(('Costes produción y ventas'!E15-'Costes produción y ventas'!C15)*'Costes produción y ventas'!H37)+(('Costes produción y ventas'!E16-'Costes produción y ventas'!C16)*'Costes produción y ventas'!H45)+(('Costes produción y ventas'!E17-'Costes produción y ventas'!C17)*'Costes produción y ventas'!H53) -> 0 | D7: =(('Costes produción y ventas'!E13-'Costes produción y ventas'!C13)*'Costes produción y ventas'!I21)+(('Costes produción y ventas'!E14-'Costes produción y ventas'!C14)*'Costes produción y ventas'!I29)+(('Costes produción y ventas'!E15-'Costes produción y ventas'!C15)*'Costes produción y ventas'!I37)+(('Costes produción y ventas'!E16-'Costes produción y ventas'!C16)*'Costes produción y ventas'!I45)+(('Costes produción y ventas'!E17-'Costes produción y ventas'!C17)*'Costes produción y ventas'!I53) -> 0 | E7: =(('Costes produción y ventas'!E13-'Costes produción y ventas'!C13)*'Costes produción y ventas'!J21)+(('Costes produción y ventas'!E14-'Costes produción y ventas'!C14)*'Costes produción y ventas'!J29)+(('Costes produción y ventas'!E15-'Costes produción y ventas'!C15)*'Costes produción y ventas'!J37)+(('Costes produción y ventas'!E16-'Costes produción y ventas'!C16)*'Costes produción y ventas'!J45)+(('Costes produción y ventas'!E17-'Costes produción y ventas'!C17)*'Costes produción y ventas'!J53) -> 105 | H7: Total IVA Repercutido | I7: =C7+D7+E7+C13+D13+E13+C19+D19+E19+C25+D25+E25 -> 8295
B8: Soportado | C8: =(('Costes produción y ventas'!E4-'Costes produción y ventas'!C4)*'Costes produción y ventas'!H21)+(('Costes produción y ventas'!E5-'Costes produción y ventas'!C5)*'Costes produción y ventas'!H29)+(('Costes produción y ventas'!E6-'Costes produción y ventas'!C6)*'Costes produción y ventas'!H37)+(('Costes produción y ventas'!E7-'Costes produción y ventas'!C7)*'Costes produción y ventas'!H45)+(('Costes produción y ventas'!E8-'Costes produción y ventas'!C8)*'Costes produción y ventas'!H53)+('Gasto Fijos y Variables'!F23+'Gasto Fijos y Variables'!F43)+'Inversión Inicial'!K12 -> 19628 | D8: =(('Costes produción y ventas'!E4-'Costes produción y ventas'!C4)*'Costes produción y ventas'!I21)+(('Costes produción y ventas'!E5-'Costes produción y ventas'!C5)*'Costes produción y ventas'!I29)+(('Costes produción y ventas'!E6-'Costes produción y ventas'!C6)*'Costes produción y ventas'!I37)+(('Costes produción y ventas'!E7-'Costes produción y ventas'!C7)*'Costes produción y ventas'!I45)+(('Costes produción y ventas'!E8-'Costes produción y ventas'!C8)*'Costes produción y ventas'!I53)+('Gasto Fijos y Variables'!J23+'Gasto Fijos y Variables'!J43) -> 255.5 | E8: =(('Costes produción y ventas'!E4-'Costes produción y ventas'!C4)*'Costes produción y ventas'!J21)+(('Costes produción y ventas'!E5-'Costes produción y ventas'!C5)*'Costes produción y ventas'!J29)+(('Costes produción y ventas'!E6-'Costes produción y ventas'!C6)*'Costes produción y ventas'!J37)+(('Costes produción y ventas'!E7-'Costes produción y ventas'!C7)*'Costes produción y ventas'!J45)+(('Costes produción y ventas'!E8-'Costes produción y ventas'!C8)*'Costes produción y ventas'!J53)+('Gasto Fijos y Variables'!N23+'Gasto Fijos y Variables'!N43) -> 282.8 | H8: Saldo Primer Trimestre | I8: =C9+D9+E9 -> -20061.3
B9: Devengado | C9: =C7-C8 -> -19628 | D9: =D7-D8 -> -255.5 | E9: =E7-E8 -> -177.8 | H9: Saldo Segundo Trimestre | I9: =C15+D15+E15 -> 172.2
H10: Saldo Tercer Trimestre | I10: =C21+D21+E21 -> 1855.42
B11: 2º TRIMESTRE | H11: Saldo Cuarto Trimestre | I11: =C27+D27+E27 -> 1897.735
C12: MES 4 | D12: MES 5 | E12: MES 6 | H12: HP deudor/acreedor por IVA | I12: =I11 -> 1897.735
B13: Repercutido | C13: =(('Costes produción y ventas'!E13-'Costes produción y ventas'!C13)*'Costes produción y ventas'!K21)+(('Costes produción y ventas'!E14-'Costes produción y ventas'!C14)*'Costes produción y ventas'!K29)+(('Costes produción y ventas'!E15-'Costes produción y ventas'!C15)*'Costes produción y ventas'!K37)+(('Costes produción y ventas'!E16-'Costes produción y ventas'!C16)*'Costes produción y ventas'!K45)+(('Costes produción y ventas'!E17-'Costes produción y ventas'!C17)*'Costes produción y ventas'!K53) -> 262.5 | D13: =(('Costes produción y ventas'!E13-'Costes produción y ventas'!C13)*'Costes produción y ventas'!L21)+(('Costes produción y ventas'!E14-'Costes produción y ventas'!C14)*'Costes produción y ventas'!L29)+(('Costes produción y ventas'!E15-'Costes produción y ventas'!C15)*'Costes produción y ventas'!L37)+(('Costes produción y ventas'!E16-'Costes produción y ventas'!C16)*'Costes produción y ventas'!L45)+(('Costes produción y ventas'!E17-'Costes produción y ventas'!C17)*'Costes produción y ventas'!L53) -> 315 | E13: =(('Costes produción y ventas'!E13-'Costes produción y ventas'!C13)*'Costes produción y ventas'!M21)+(('Costes produción y ventas'!E14-'Costes produción y ventas'!C14)*'Costes produción y ventas'!M29)+(('Costes produción y ventas'!E15-'Costes produción y ventas'!C15)*'Costes produción y ventas'!M37)+(('Costes produción y ventas'!E16-'Costes produción y ventas'!C16)*'Costes produción y ventas'!M45)+(('Costes produción y ventas'!E17-'Costes produción y ventas'!C17)*'Costes produción y ventas'!M53) -> 682.5
B14: Soportado | C14: =(('Costes produción y ventas'!E4-'Costes produción y ventas'!C4)*'Costes produción y ventas'!K21)+(('Costes produción y ventas'!E5-'Costes produción y ventas'!C5)*'Costes produción y ventas'!K29)+(('Costes produción y ventas'!E6-'Costes produción y ventas'!C6)*'Costes produción y ventas'!K37)+(('Costes produción y ventas'!E7-'Costes produción y ventas'!C7)*'Costes produción y ventas'!K45)+(('Costes produción y ventas'!E8-'Costes produción y ventas'!C8)*'Costes produción y ventas'!K53)+('Gasto Fijos y Variables'!R23+'Gasto Fijos y Variables'!R43) -> 327.95 | D14: =(('Costes produción y ventas'!E4-'Costes produción y ventas'!C4)*'Costes produción y ventas'!L21)+(('Costes produción y ventas'!E5-'Costes produción y ventas'!C5)*'Costes produción y ventas'!L29)+(('Costes produción y ventas'!E6-'Costes produción y ventas'!C6)*'Costes produción y ventas'!L37)+(('Costes produción y ventas'!E7-'Costes produción y ventas'!C7)*'Costes produción y ventas'!L45)+(('Costes produción y ventas'!E8-'Costes produción y ventas'!C8)*'Costes produción y ventas'!L53)+('Gasto Fijos y Variables'!V23+'Gasto Fijos y Variables'!V43) -> 341.6 | E14: =(('Costes produción y ventas'!E4-'Costes produción y ventas'!C4)*'Costes produción y ventas'!M21)+(('Costes produción y ventas'!E5-'Costes produción y ventas'!C5)*'Costes produción y ventas'!M29)+(('Costes produción y ventas'!E6-'Costes produción y ventas'!C6)*'Costes produción y ventas'!M37)+(('Costes produción y ventas'!E7-'Costes produción y ventas'!C7)*'Costes produción y ventas'!M45)+(('Costes produción y ventas'!E8-'Costes produción y ventas'!C8)*'Costes produción y ventas'!M53)+('Gasto Fijos y Variables'!Z23+'Gasto Fijos y Variables'!Z43) -> 418.25
B15: Devengado | C15: =C13-C14 -> -65.45 | D15: =D13-D14 -> -26.6 | E15: =E13-E14 -> 264.25
B17: 3º TRIMESTRE
C18: MES 7 | D18: MES 8 | E18: MES 9
B19: Repercutido | C19: =(('Costes produción y ventas'!E13-'Costes produción y ventas'!C13)*'Costes produción y ventas'!N21)+(('Costes produción y ventas'!E14-'Costes produción y ventas'!C14)*'Costes produción y ventas'!N29)+(('Costes produción y ventas'!E15-'Costes produción y ventas'!C15)*'Costes produción y ventas'!N37)+(('Costes produción y ventas'!E16-'Costes produción y ventas'!C16)*'Costes produción y ventas'!N45)+(('Costes produción y ventas'!E17-'Costes produción y ventas'!C17)*'Costes produción y ventas'!N53) -> 987 | D19: =(('Costes produción y ventas'!E13-'Costes produción y ventas'!C13)*'Costes produción y ventas'!O21)+(('Costes produción y ventas'!E14-'Costes produción y ventas'!C14)*'Costes produción y ventas'!O29)+(('Costes produción y ventas'!E15-'Costes produción y ventas'!C15)*'Costes produción y ventas'!O37)+(('Costes produción y ventas'!E16-'Costes produción y ventas'!C16)*'Costes produción y ventas'!O45)+(('Costes produción y ventas'!E17-'Costes produción y ventas'!C17)*'Costes produción y ventas'!O53) -> 1284.5 | E19: =(('Costes produción y ventas'!E13-'Costes produción y ventas'!C13)*'Costes produción y ventas'!P21)+(('Costes produción y ventas'!E14-'Costes produción y ventas'!C14)*'Costes produción y ventas'!P29)+(('Costes produción y ventas'!E15-'Costes produción y ventas'!C15)*'Costes produción y ventas'!P37)+(('Costes produción y ventas'!E16-'Costes produción y ventas'!C16)*'Costes produción y ventas'!P45)+(('Costes produción y ventas'!E17-'Costes produción y ventas'!C17)*'Costes produción y ventas'!P53) -> 1337
B20: Soportado | C20: =(('Costes produción y ventas'!E4-'Costes produción y ventas'!C4)*'Costes produción y ventas'!N21)+(('Costes produción y ventas'!E5-'Costes produción y ventas'!C5)*'Costes produción y ventas'!N29)+(('Costes produción y ventas'!E6-'Costes produción y ventas'!C6)*'Costes produción y ventas'!N37)+(('Costes produción y ventas'!E7-'Costes produción y ventas'!C7)*'Costes produción y ventas'!N45)+(('Costes produción y ventas'!E8-'Costes produción y ventas'!C8)*'Costes produción y ventas'!N53)+('Gasto Fijos y Variables'!AD23+'Gasto Fijos y Variables'!AD43) -> 515.9 | D20: =(('Costes produción y ventas'!E4-'Costes produción y ventas'!C4)*'Costes produción y ventas'!O21)+(('Costes produción y ventas'!E5-'Costes produción y ventas'!C5)*'Costes produción y ventas'!O29)+(('Costes produción y ventas'!E6-'Costes produción y ventas'!C6)*'Costes produción y ventas'!O37)+(('Costes produción y ventas'!E7-'Costes produción y ventas'!C7)*'Costes produción y ventas'!O45)+(('Costes produción y ventas'!E8-'Costes produción y ventas'!C8)*'Costes produción y ventas'!O53)+('Gasto Fijos y Variables'!AH23+'Gasto Fijos y Variables'!AH43) -> 611.765 | E20: =(('Costes produción y ventas'!E4-'Costes produción y ventas'!C4)*'Costes produción y ventas'!P21)+(('Costes produción y ventas'!E5-'Costes produción y ventas'!C5)*'Costes produción y ventas'!P29)+(('Costes produción y ventas'!E6-'Costes produción y ventas'!C6)*'Costes produción y ventas'!P37)+(('Costes produción y ventas'!E7-'Costes produción y ventas'!C7)*'Costes produción y ventas'!P45)+(('Costes produción y ventas'!E8-'Costes produción y ventas'!C8)*'Costes produción y ventas'!P53)+('Gasto Fijos y Variables'!AL23+'Gasto Fijos y Variables'!AL43) -> 625.415
B21: Devengado | C21: =C19-C20 -> 471.1 | D21: =D19-D20 -> 672.735 | E21: =E19-E20 -> 711.585
B23: 4º TRIMESTRE
C24: MES 10 | D24: MES 11 | E24: MES 12
B25: Repercutido | C25: =(('Costes produción y ventas'!E13-'Costes produción y ventas'!C13)*'Costes produción y ventas'!Q21)+(('Costes produción y ventas'!E14-'Costes produción y ventas'!C14)*'Costes produción y ventas'!Q29)+(('Costes produción y ventas'!E15-'Costes produción y ventas'!C15)*'Costes produción y ventas'!Q37)+(('Costes produción y ventas'!E16-'Costes produción y ventas'!C16)*'Costes produción y ventas'!Q45)+(('Costes produción y ventas'!E17-'Costes produción y ventas'!C17)*'Costes produción y ventas'!Q53) -> 1389.5 | D25: =(('Costes produción y ventas'!E13-'Costes produción y ventas'!C13)*'Costes produción y ventas'!R21)+(('Costes produción y ventas'!E14-'Costes produción y ventas'!C14)*'Costes produción y ventas'!R29)+(('Costes produción y ventas'!E15-'Costes produción y ventas'!C15)*'Costes produción y ventas'!R37)+(('Costes produción y ventas'!E16-'Costes produción y ventas'!C16)*'Costes produción y ventas'!R45)+(('Costes produción y ventas'!E17-'Costes produción y ventas'!C17)*'Costes produción y ventas'!R53) -> 1039.5 | E25: =(('Costes produción y ventas'!E13-'Costes produción y ventas'!C13)*'Costes produción y ventas'!S21)+(('Costes produción y ventas'!E14-'Costes produción y ventas'!C14)*'Costes produción y ventas'!S29)+(('Costes produción y ventas'!E15-'Costes produción y ventas'!C15)*'Costes produción y ventas'!S37)+(('Costes produción y ventas'!E16-'Costes produción y ventas'!C16)*'Costes produción y ventas'!S45)+(('Costes produción y ventas'!E17-'Costes produción y ventas'!C17)*'Costes produción y ventas'!S53) -> 892.5
B26: Soportado | C26: =(('Costes produción y ventas'!E4-'Costes produción y ventas'!C4)*'Costes produción y ventas'!Q21)+(('Costes produción y ventas'!E5-'Costes produción y ventas'!C5)*'Costes produción y ventas'!Q29)+(('Costes produción y ventas'!E6-'Costes produción y ventas'!C6)*'Costes produción y ventas'!Q37)+(('Costes produción y ventas'!E7-'Costes produción y ventas'!C7)*'Costes produción y ventas'!Q45)+(('Costes produción y ventas'!E8-'Costes produción y ventas'!C8)*'Costes produción y ventas'!Q53)+('Gasto Fijos y Variables'!AP23+'Gasto Fijos y Variables'!AP43) -> 639.065 | D26: =(('Costes produción y ventas'!E4-'Costes produción y ventas'!C4)*'Costes produción y ventas'!R21)+(('Costes produción y ventas'!E5-'Costes produción y ventas'!C5)*'Costes produción y ventas'!R29)+(('Costes produción y ventas'!E6-'Costes produción y ventas'!C6)*'Costes produción y ventas'!R37)+(('Costes produción y ventas'!E7-'Costes produción y ventas'!C7)*'Costes produción y ventas'!R45)+(('Costes produción y ventas'!E8-'Costes produción y ventas'!C8)*'Costes produción y ventas'!R53)+('Gasto Fijos y Variables'!AT23+'Gasto Fijos y Variables'!AT43) -> 548.45 | E26: =(('Costes produción y ventas'!E4-'Costes produción y ventas'!C4)*'Costes produción y ventas'!S21)+(('Costes produción y ventas'!E5-'Costes produción y ventas'!C5)*'Costes produción y ventas'!S29)+(('Costes produción y ventas'!E6-'Costes produción y ventas'!C6)*'Costes produción y ventas'!S37)+(('Costes produción y ventas'!E7-'Costes produción y ventas'!C7)*'Costes produción y ventas'!S45)+(('Costes produción y ventas'!E8-'Costes produción y ventas'!C8)*'Costes produción y ventas'!S53)+('Gasto Fijos y Variables'!AX23+'Gasto Fijos y Variables'!AX43) -> 236.25
B27: Devengado | C27: =C25-C26 -> 750.435 | D27: =D25-D26 -> 491.05 | E27: =E25-E26 -> 656.25
B29: Esta información se obtiene de manera automática, teniendo en cuenta datos que se han introducido en apartados anteriores.

Sheet Gasto Fijos y Variables
B3: Gastos Fijos y Variables
D5: MES 1 | H5: MES 2 | L5: MES 3 | P5: MES 4 | T5: MES 5 | X5: MES 6 | AB5: MES 7 | AF5: MES 8 | AJ5: MES 9 | AN5: MES 10 | AR5: MES 11 | AV5: MES 12
B6: GASTOS FIJOS | C6: Imp Total S/IVA | D6: imp. Sin IVA | E6: % | F6: imp. IVA | G6: Total | H6: imp. Sin IVA | I6: % | J6: imp. IVA | K6: Total | L6: imp. Sin IVA | M6: % | N6: imp. IVA | O6: Total | P6: imp. Sin IVA | Q6: % | R6: imp. IVA | S6: Total | T6: imp. Sin IVA | U6: % | V6: imp. IVA | W6: Total | X6: imp. Sin IVA | Y6: % | Z6: imp. IVA | AA6: Total | AB6: imp. Sin IVA | AC6: % | AD6: imp. IVA | AE6: Total | AF6: imp. Sin IVA | AG6: % | AH6: imp. IVA | AI6: Total | AJ6: imp. Sin IVA | AK6: % | AL6: imp. IVA | AM6: Total | AN6: imp. Sin IVA | AO6: % | AP6: imp. IVA | AQ6: Total | AR6: imp. Sin IVA | AS6: % | AT6: imp. IVA | AU6: Total | AV6: imp. Sin IVA | AW6: % | AX6: imp. IVA | AY6: Total | AZ6: Salir Exacto
B7: Agua | C7: 0 | D7: 0 | E7: 0.21 | F7: =D7*E7 -> 0 | G7: =D7+F7 -> 0 | H7: 0 | I7: 0.21 | J7: =H7*I7 -> 0 | K7: =H7+J7 -> 0 | L7: 0 | M7: 0.21 | N7: =L7*M7 -> 0 | O7: =L7+N7 -> 0 | P7: 0 | Q7: 0.21 | R7: =P7*Q7 -> 0 | S7: =P7+R7 -> 0 | T7: 0 | U7: 0.21 | V7: =T7*U7 -> 0 | W7: =T7+V7 -> 0 | X7: 0 | Y7: 0.21 | Z7: =X7*Y7 -> 0 | AA7: =X7+Z7 -> 0 | AB7: 0 | AC7: 0.21 | AD7: =AB7*AC7 -> 0 | AE7: =AB7+AD7 -> 0 | AF7: 0 | AG7: 0.21 | AH7: =AF7*AG7 -> 0 | AI7: =AF7+AH7 -> 0 | AJ7: 0 | AK7: 0.21 | AL7: =AJ7*AK7 -> 0 | AM7: =AJ7+AL7 -> 0 | AN7: 0 | AO7: 0.21 | AP7: =AN7*AO7 -> 0 | AQ7: =AN7+AP7 -> 0 | AR7: 0 | AS7: 0.21 | AT7: =AR7*AS7 -> 0 | AU7: =AR7+AT7 -> 0 | AV7: 0 | AW7: 0.21 | AX7: =AV7*AW7 -> 0 | AY7: =AV7+AX7 -> 0 | AZ7: =D7+H7+L7+P7+T7+X7+AB7+AF7+AJ7+AN7+AR7+AV7-C7 -> 0
B8: Luz | C8: 0 | D8: 0 | E8: 0.21 | F8: =D8*E8 -> 0 | G8: =D8+F8 -> 0 | H8: 0 | I8: 0.21 | J8: =H8*I8 -> 0 | K8: =H8+J8 -> 0 | L8: 0 | M8: 0.21 | N8: =L8*M8 -> 0 | O8: =L8+N8 -> 0 | P8: 0 | Q8: 0.21 | R8: =P8*Q8 -> 0 | S8: =P8+R8 -> 0 | T8: 0 | U8: 0.21 | V8: =T8*U8 -> 0 | W8: =T8+V8 -> 0 | X8: 0 | Y8: 0.21 | Z8: =X8*Y8 -> 0 | AA8: =X8+Z8 -> 0 | AB8: 0 | AC8: 0.21 | AD8: =AB8*AC8 -> 0 | AE8: =AB8+AD8 -> 0 | AF8: 0 | AG8: 0.21 | AH8: =AF8*AG8 -> 0 | AI8: =AF8+AH8 -> 0 | AJ8: 0 | AK8: 0.21 | AL8: =AJ8*AK8 -> 0 | AM8: =AJ8+AL8 -> 0 | AN8: 0 | AO8: 0.21 | AP8: =AN8*AO8 -> 0 | AQ8: =AN8+AP8 -> 0 | AR8: 0 | AS8: 0.21 | AT8: =AR8*AS8 -> 0 | AU8: =AR8+AT8 -> 0 | AV8: 0 | AW8: 0.21 | AX8: =AV8*AW8 -> 0 | AY8: =AV8+AX8 -> 0 | AZ8: =D8+H8+L8+P8+T8+X8+AB8+AF8+AJ8+AN8+AR8+AV8-C8 -> 0
B9: Gas | C9: 0 | D9: 0 | E9: 0.21 | F9: =D9*E9 -> 0 | G9: =D9+F9 -> 0 | H9: 0 | I9: 0.21 | J9: =H9*I9 -> 0 | K9: =H9+J9 -> 0 | L9: 0 | M9: 0.21 | N9: =L9*M9 -> 0 | O9: =L9+N9 -> 0 | P9: 0 | Q9: 0.21 | R9: =P9*Q9 -> 0 | S9: =P9+R9 -> 0 | T9: 0 | U9: 0.21 | V9: =T9*U9 -> 0 | W9: =T9+V9 -> 0 | X9: 0 | Y9: 0.21 | Z9: =X9*Y9 -> 0 | AA9: =X9+Z9 -> 0 | AB9: 0 | AC9: 0.21 | AD9: =AB9*AC9 -> 0 | AE9: =AB9+AD9 -> 0 | AF9: 0 | AG9: 0.21 | AH9: =AF9*AG9 -> 0 | AI9: =AF9+AH9 -> 0 | AJ9: 0 | AK9: 0.21 | AL9: =AJ9*AK9 -> 0 | AM9: =AJ9+AL9 -> 0 | AN9: 0 | AO9: 0.21 | AP9: =AN9*AO9 -> 0 | AQ9: =AN9+AP9 -> 0 | AR9: 0 | AS9: 0.21 | AT9: =AR9*AS9 -> 0 | AU9: =AR9+AT9 -> 0 | AV9: 0 | AW9: 0.21 | AX9: =AV9*AW9 -> 0 | AY9: =AV9+AX9 -> 0 | AZ9: =D9+H9+L9+P9+T9+X9+AB9+AF9+AJ9+AN9+AR9+AV9-C9 -> 0
B10: Internet | C10: 1800 | D10: 150 | E10: 0.21 | F10: =D10*E10 -> 31.5 | G10: =D10+F10 -> 181.5 | H10: 150 | I10: 0.21 | J10: =H10*I10 -> 31.5 | K10: =H10+J10 -> 181.5 | L10: 150 | M10: 0.21 | N10: =L10*M10 -> 31.5 | O10: =L10+N10 -> 181.5 | P10: 150 | Q10: 0.21 | R10: =P10*Q10 -> 31.5 | S10: =P10+R10 -> 181.5 | T10: 150 | U10: 0.21 | V10: =T10*U10 -> 31.5 | W10: =T10+V10 -> 181.5 | X10: 150 | Y10: 0.21 | Z10: =X10*Y10 -> 31.5 | AA10: =X10+Z10 -> 181.5 | AB10: 150 | AC10: 0.21 | AD10: =AB10*AC10 -> 31.5 | AE10: =AB10+AD10 -> 181.5 | AF10: 150 | AG10: 0.21 | AH10: =AF10*AG10 -> 31.5 | AI10: =AF10+AH10 -> 181.5 | AJ10: 150 | AK10: 0.21 | AL10: =AJ10*AK10 -> 31.5 | AM10: =AJ10+AL10 -> 181.5 | AN10: 150 | AO10: 0.21 | AP10: =AN10*AO10 -> 31.5 | AQ10: =AN10+AP10 -> 181.5 | AR10: 150 | AS10: 0.21 | AT10: =AR10*AS10 -> 31.5 | AU10: =AR10+AT10 -> 181.5 | AV10: 0 | AW10: 0.21 | AX10: =AV10*AW10 -> 0 | AY10: =AV10+AX10 -> 0 | AZ10: =D10+H10+L10+P10+T10+X10+AB10+AF10+AJ10+AN10+AR10+AV10-C10 -> -150
B11: Telefonia | C11: 0 | D11: 0 | E11: 0.21 | F11: =D11*E11 -> 0 | G11: =D11+F11 -> 0 | H11: 0 | I11: 0.21 | J11: =H11*I11 -> 0 | K11: =H11+J11 -> 0 | L11: 0 | M11: 0.21 | N11: =L11*M11 -> 0 | O11: =L11+N11 -> 0 | P11: 0 | Q11: 0.21 | R11: =P11*Q11 -> 0 | S11: =P11+R11 -> 0 | T11: 0 | U11: 0.21 | V11: =T11*U11 -> 0 | W11: =T11+V11 -> 0 | X11: 0 | Y11: 0.21 | Z11: =X11*Y11 -> 0 | AA11: =X11+Z11 -> 0 | AB11: 0 | AC11: 0.21 | AD11: =AB11*AC11 -> 0 | AE11: =AB11+AD11 -> 0 | AF11: 0 | AG11: 0.21 | AH11: =AF11*AG11 -> 0 | AI11: =AF11+AH11 -> 0 | AJ11: 0 | AK11: 0.21 | AL11: =AJ11*AK11 -> 0 | AM11: =AJ11+AL11 -> 0 | AN11: 0 | AO11: 0.21 | AP11: =AN11*AO11 -> 0 | AQ11: =AN11+AP11 -> 0 | AR11: 0 | AS11: 0.21 | AT11: =AR11*AS11 -> 0 | AU11: =AR11+AT11 -> 0 | AV11: 0 | AW11: 0.21 | AX11: =AV11*AW11 -> 0 | AY11: =AV11+AX11 -> 0 | AZ11: =D11+H11+L11+P11+T11+X11+AB11+AF11+AJ11+AN11+AR11+AV11-C11 -> 0
B12: Alquiler | C12: 3600 | D12: 300 | E12: 0.21 | F12: =D12*E12 -> 63 | G12: =D12+F12 -> 363 | H12: 300 | I12: 0.21 | J12: =H12*I12 -> 63 | K12: =H12+J12 -> 363 | L12: 300 | M12: 0.21 | N12: =L12*M12 -> 63 | O12: =L12+N12 -> 363 | P12: 300 | Q12: 0.21 | R12: =P12*Q12 -> 63 | S12: =P12+R12 -> 363 | T12: 300 | U12: 0.21 | V12: =T12*U12 -> 63 | W12: =T12+V12 -> 363 | X12: 300 | Y12: 0.21 | Z12: =X12*Y12 -> 63 | AA12: =X12+Z12 -> 363 | AB12: 300 | AC12: 0.21 | AD12: =AB12*AC12 -> 63 | AE12: =AB12+AD12 -> 363 | AF12: 300 | AG12: 0.21 | AH12: =AF12*AG12 -> 63 | AI12: =AF12+AH12 -> 363 | AJ12: 300 | AK12: 0.21 | AL12: =AJ12*AK12 -> 63 | AM12: =AJ12+AL12 -> 363 | AN12: 300 | AO12: 0.21 | AP12: =AN12*AO12 -> 63 | AQ12: =AN12+AP12 -> 363 | AR12: 300 | AS12: 0.21 | AT12: =AR12*AS12 -> 63 | AU12: =AR12+AT12 -> 363 | AV12: 0 | AW12: 0.21 | AX12: =AV12*AW12 -> 0 | AY12: =AV12+AX12 -> 0 | AZ12: =D12+H12+L12+P12+T12+X12+AB12+AF12+AJ12+AN12+AR12+AV12-C12 -> -300
B13: Seguros | C13: 1200 | D13: 100 | E13: 0 | G13: =D13 -> 100 | H13: 100 | I13: 0 | K13: =H13 -> 100 | L13: 100 | M13: 0 | O13: =L13 -> 100 | P13: 100 | Q13: 0 | S13: =P13 -> 100 | T13: 100 | U13: 0 | W13: =T13 -> 100 | X13: 100 | Y13: 0 | AA13: =X13 -> 100 | AB13: 100 | AC13: 0 | AE13: =AB13 -> 100 | AF13: 100 | AG13: 0 | AI13: =AF13 -> 100 | AJ13: 100 | AK13: 0 | AM13: =AJ13 -> 100 | AN13: 100 | AO13: 0 | AQ13: =AN13 -> 100 | AR13: 100 | AS13: 0 | AU13: =AR13 -> 100 | AV13: 0 | AW13: 0 | AY13: =AV13 -> 0 | AZ13: =D13+H13+L13+P13+T13+X13+AB13+AF13+AJ13+AN13+AR13+AV13-C13 -> -100
B14: Gastos de gestoria | C14: 2400 | D14: 200 | E14: 0.21 | F14: =D14*E14 -> 42 | G14: =D14+F14 -> 242 | H14: 200 | I14: 0.21 | J14: =H14*I14 -> 42 | K14: =H14+J14 -> 242 | L14: 200 | M14: 0.21 | N14: =L14*M14 -> 42 | O14: =L14+N14 -> 242 | P14: 200 | Q14: 0.21 | R14: =P14*Q14 -> 42 | S14: =P14+R14 -> 242 | T14: 200 | U14: 0.21 | V14: =T14*U14 -> 42 | W14: =T14+V14 -> 242 | X14: 200 | Y14: 0.21 | Z14: =X14*Y14 -> 42 | AA14: =X14+Z14 -> 242 | AB14: 200 | AC14: 0.21 | AD14: =AB14*AC14 -> 42 | AE14: =AB14+AD14 -> 242 | AF14: 200 | AG14: 0.21 | AH14: =AF14*AG14 -> 42 | AI14: =AF14+AH14 -> 242 | AJ14: 200 | AK14: 0.21 | AL14: =AJ14*AK14 -> 42 | AM14: =AJ14+AL14 -> 242 | AN14: 200 | AO14: 0.21 | AP14: =AN14*AO14 -> 42 | AQ14: =AN14+AP14 -> 242 | AR14: 200 | AS14: 0.21 | AT14: =AR14*AS14 -> 42 | AU14: =AR14+AT14 -> 242 | AV14: 0 | AW14: 0.21 | AX14: =AV14*AW14 -> 0 | AY14: =AV14+AX14 -> 0 | AZ14: =D14+H14+L14+P14+T14+X14+AB14+AF14+AJ14+AN14+AR14+AV14-C14 -> -200
B15: Marketing | C15: 4000 | D15: 333.33333 | E15: 0.21 | F15: =D15*E15 -> 70 | G15: =D15+F15 -> 403.33333 | H15: 333.33333 | I15: 0.21 | J15: =H15*I15 -> 70 | K15: =H15+J15 -> 403.33333 | L15: 333.33333 | M15: 0.21 | N15: =L15*M15 -> 70 | O15: =L15+N15 -> 403.33333 | P15: 333.33333 | Q15: 0.21 | R15: =P15*Q15 -> 70 | S15: =P15+R15 -> 403.33333 | T15: 333.33333 | U15: 0.21 | V15: =T15*U15 -> 70 | W15: =T15+V15 -> 403.33333 | X15: 333.33333 | Y15: 0.21 | Z15: =X15*Y15 -> 70 | AA15: =X15+Z15 -> 403.33333 | AB15: 333.33333 | AC15: 0.21 | AD15: =AB15*AC15 -> 70 | AE15: =AB15+AD15 -> 403.33333 | AF15: 333.33333 | AG15: 0.21 | AH15: =AF15*AG15 -> 70 | AI15: =AF15+AH15 -> 403.33333 | AJ15: 333.33333 | AK15: 0.21 | AL15: =AJ15*AK15 -> 70 | AM15: =AJ15+AL15 -> 403.33333 | AN15: 333.33333 | AO15: 0.21 | AP15: =AN15*AO15 -> 70 | AQ15: =AN15+AP15 -> 403.33333 | AR15: 333.33333 | AS15: 0.21 | AT15: =AR15*AS15 -> 70 | AU15: =AR15+AT15 -> 403.33333 | AV15: 0 | AW15: 0.21 | AX15: =AV15*AW15 -> 0 | AY15: =AV15+AX15 -> 0 | AZ15: =D15+H15+L15+P15+T15+X15+AB15+AF15+AJ15+AN15+AR15+AV15-C15 -> -333.33333
B16: Sueldo de autónomo — incluido en Gastos de Personal (no duplicar) | C16: 0 | D16: 0 | E16: 0 | G16: =D16 -> 0 | H16: 0 | I16: 0 | K16: =H16 -> 0 | L16: 0 | M16: 0 | O16: =L16 -> 0 | P16: 0 | Q16: 0 | S16: =P16 -> 0 | T16: 0 | U16: 0 | W16: =T16 -> 0 | X16: 0 | Y16: 0 | AA16: =X16 -> 0 | AB16: 0 | AC16: 0 | AE16: =AB16 -> 0 | AF16: 0 | AG16: 0 | AI16: =AF16 -> 0 | AJ16: 0 | AK16: 0 | AM16: =AJ16 -> 0 | AN16: 0 | AO16: 0 | AQ16: =AN16 -> 0 | AR16: 0 | AS16: 0 | AU16: =AR16 -> 0 | AV16: 0 | AW16: 0 | AY16: =AV16 -> 0 | AZ16: =D16+H16+L16+P16+T16+X16+AB16+AF16+AJ16+AN16+AR16+AV16-C16 -> 0
B17: RETA — incluido en Gastos de Personal (4.800 €/año; no duplicar) | C17: 0 | D17: 0 | E17: 0 | G17: =D17 -> 0 | H17: 0 | I17: 0 | K17: =H17 -> 0 | L17: 0 | M17: 0 | O17: =L17 -> 0 | P17: 0 | Q17: 0 | S17: =P17 -> 0 | T17: 0 | U17: 0 | W17: =T17 -> 0 | X17: 0 | Y17: 0 | AA17: =X17 -> 0 | AB17: 0 | AC17: 0 | AE17: =AB17 -> 0 | AF17: 0 | AG17: 0 | AI17: =AF17 -> 0 | AJ17: 0 | AK17: 0 | AM17: =AJ17 -> 0 | AN17: 0 | AO17: 0 | AQ17: =AN17 -> 0 | AR17: 0 | AS17: 0 | AU17: =AR17 -> 0 | AV17: 0 | AW17: 0 | AY17: =AV17 -> 0 | AZ17: =D17+H17+L17+P17+T17+X17+AB17+AF17+AJ17+AN17+AR17+AV17-C17 -> 0
B18: … | C18: 0 | D18: 0 | E18: 0.21 | F18: =D18*E18 -> 0 | G18: =D18+F18 -> 0 | H18: 0 | I18: 0.21 | J18: =H18*I18 -> 0 | K18: =H18+J18 -> 0 | L18: 0 | M18: 0.21 | N18: =L18*M18 -> 0 | O18: =L18+N18 -> 0 | P18: 0 | Q18: 0.21 | R18: =P18*Q18 -> 0 | S18: =P18+R18 -> 0 | T18: 0 | U18: 0.21 | V18: =T18*U18 -> 0 | W18: =T18+V18 -> 0 | X18: 0 | Y18: 0.21 | Z18: =X18*Y18 -> 0 | AA18: =X18+Z18 -> 0 | AB18: 0 | AC18: 0.21 | AD18: =AB18*AC18 -> 0 | AE18: =AB18+AD18 -> 0 | AF18: 0 | AG18: 0.21 | AH18: =AF18*AG18 -> 0 | AI18: =AF18+AH18 -> 0 | AJ18: 0 | AK18: 0.21 | AL18: =AJ18*AK18 -> 0 | AM18: =AJ18+AL18 -> 0 | AN18: 0 | AO18: 0.21 | AP18: =AN18*AO18 -> 0 | AQ18: =AN18+AP18 -> 0 | AR18: 0 | AS18: 0.21 | AT18: =AR18*AS18 -> 0 | AU18: =AR18+AT18 -> 0 | AV18: 0 | AW18: 0.21 | AX18: =AV18*AW18 -> 0 | AY18: =AV18+AX18 -> 0 | AZ18: =D18+H18+L18+P18+T18+X18+AB18+AF18+AJ18+AN18+AR18+AV18-C18 -> 0
B19: … | C19: 0 | D19: 0 | E19: 0.21 | F19: =D19*E19 -> 0 | G19: =D19+F19 -> 0 | H19: 0 | I19: 0.21 | J19: =H19*I19 -> 0 | K19: =H19+J19 -> 0 | L19: 0 | M19: 0.21 | N19: =L19*M19 -> 0 | O19: =L19+N19 -> 0 | P19: 0 | Q19: 0.21 | R19: =P19*Q19 -> 0 | S19: =P19+R19 -> 0 | T19: 0 | U19: 0.21 | V19: =T19*U19 -> 0 | W19: =T19+V19 -> 0 | X19: 0 | Y19: 0.21 | Z19: =X19*Y19 -> 0 | AA19: =X19+Z19 -> 0 | AB19: 0 | AC19: 0.21 | AD19: =AB19*AC19 -> 0 | AE19: =AB19+AD19 -> 0 | AF19: 0 | AG19: 0.21 | AH19: =AF19*AG19 -> 0 | AI19: =AF19+AH19 -> 0 | AJ19: 0 | AK19: 0.21 | AL19: =AJ19*AK19 -> 0 | AM19: =AJ19+AL19 -> 0 | AN19: 0 | AO19: 0.21 | AP19: =AN19*AO19 -> 0 | AQ19: =AN19+AP19 -> 0 | AR19: 0 | AS19: 0.21 | AT19: =AR19*AS19 -> 0 | AU19: =AR19+AT19 -> 0 | AV19: 0 | AW19: 0.21 | AX19: =AV19*AW19 -> 0 | AY19: =AV19+AX19 -> 0 | AZ19: =D19+H19+L19+P19+T19+X19+AB19+AF19+AJ19+AN19+AR19+AV19-C19 -> 0
B20: … | C20: 0 | D20: 0 | E20: 0.21 | F20: =D20*E20 -> 0 | G20: =D20+F20 -> 0 | H20: 0 | I20: 0.21 | J20: =H20*I20 -> 0 | K20: =H20+J20 -> 0 | L20: 0 | M20: 0.21 | N20: =L20*M20 -> 0 | O20: =L20+N20 -> 0 | P20: 0 | Q20: 0.21 | R20: =P20*Q20 -> 0 | S20: =P20+R20 -> 0 | T20: 0 | U20: 0.21 | V20: =T20*U20 -> 0 | W20: =T20+V20 -> 0 | X20: 0 | Y20: 0.21 | Z20: =X20*Y20 -> 0 | AA20: =X20+Z20 -> 0 | AB20: 0 | AC20: 0.21 | AD20: =AB20*AC20 -> 0 | AE20: =AB20+AD20 -> 0 | AF20: 0 | AG20: 0.21 | AH20: =AF20*AG20 -> 0 | AI20: =AF20+AH20 -> 0 | AJ20: 0 | AK20: 0.21 | AL20: =AJ20*AK20 -> 0 | AM20: =AJ20+AL20 -> 0 | AN20: 0 | AO20: 0.21 | AP20: =AN20*AO20 -> 0 | AQ20: =AN20+AP20 -> 0 | AR20: 0 | AS20: 0.21 | AT20: =AR20*AS20 -> 0 | AU20: =AR20+AT20 -> 0 | AV20: 0 | AW20: 0.21 | AX20: =AV20*AW20 -> 0 | AY20: =AV20+AX20 -> 0 | AZ20: =D20+H20+L20+P20+T20+X20+AB20+AF20+AJ20+AN20+AR20+AV20-C20 -> 0
B21: … | C21: 0 | D21: 0 | E21: 0.21 | F21: =D21*E21 -> 0 | G21: =D21+F21 -> 0 | H21: 0 | I21: 0.21 | J21: =H21*I21 -> 0 | K21: =H21+J21 -> 0 | L21: 0 | M21: 0.21 | N21: =L21*M21 -> 0 | O21: =L21+N21 -> 0 | P21: 0 | Q21: 0.21 | R21: =P21*Q21 -> 0 | S21: =P21+R21 -> 0 | T21: 0 | U21: 0.21 | V21: =T21*U21 -> 0 | W21: =T21+V21 -> 0 | X21: 0 | Y21: 0.21 | Z21: =X21*Y21 -> 0 | AA21: =X21+Z21 -> 0 | AB21: 0 | AC21: 0.21 | AD21: =AB21*AC21 -> 0 | AE21: =AB21+AD21 -> 0 | AF21: 0 | AG21: 0.21 | AH21: =AF21*AG21 -> 0 | AI21: =AF21+AH21 -> 0 | AJ21: 0 | AK21: 0.21 | AL21: =AJ21*AK21 -> 0 | AM21: =AJ21+AL21 -> 0 | AN21: 0 | AO21: 0.21 | AP21: =AN21*AO21 -> 0 | AQ21: =AN21+AP21 -> 0 | AR21: 0 | AS21: 0.21 | AT21: =AR21*AS21 -> 0 | AU21: =AR21+AT21 -> 0 | AV21: 0 | AW21: 0.21 | AX21: =AV21*AW21 -> 0 | AY21: =AV21+AX21 -> 0 | AZ21: =D21+H21+L21+P21+T21+X21+AB21+AF21+AJ21+AN21+AR21+AV21-C21 -> 0
B22: … | C22: 0 | D22: 0 | E22: 0.21 | F22: =D22*E22 -> 0 | G22: =D22+F22 -> 0 | H22: 0 | I22: 0.21 | J22: =H22*I22 -> 0 | K22: =H22+J22 -> 0 | L22: 0 | M22: 0.21 | N22: =L22*M22 -> 0 | O22: =L22+N22 -> 0 | P22: 0 | Q22: 0.21 | R22: =P22*Q22 -> 0 | S22: =P22+R22 -> 0 | T22: 0 | U22: 0.21 | V22: =T22*U22 -> 0 | W22: =T22+V22 -> 0 | X22: 0 | Y22: 0.21 | Z22: =X22*Y22 -> 0 | AA22: =X22+Z22 -> 0 | AB22: 0 | AC22: 0.21 | AD22: =AB22*AC22 -> 0 | AE22: =AB22+AD22 -> 0 | AF22: 0 | AG22: 0.21 | AH22: =AF22*AG22 -> 0 | AI22: =AF22+AH22 -> 0 | AJ22: 0 | AK22: 0.21 | AL22: =AJ22*AK22 -> 0 | AM22: =AJ22+AL22 -> 0 | AN22: 0 | AO22: 0.21 | AP22: =AN22*AO22 -> 0 | AQ22: =AN22+AP22 -> 0 | AR22: 0 | AS22: 0.21 | AT22: =AR22*AS22 -> 0 | AU22: =AR22+AT22 -> 0 | AV22: 0 | AW22: 0.21 | AX22: =AV22*AW22 -> 0 | AY22: =AV22+AX22 -> 0 | AZ22: =D22+H22+L22+P22+T22+X22+AB22+AF22+AJ22+AN22+AR22+AV22-C22 -> 0
B23: TOTAL DE GASTOS FIJOS | C23: =SUM(C7:C22) -> 13000 | D23: =SUM(D7:D22) -> 1083.3333 | F23: =SUM(F7:F22) -> 206.5 | G23: =SUM(G7:G22) -> 1289.8333 | H23: =SUM(H7:H22) -> 1083.3333 | J23: =SUM(J7:J22) -> 206.5 | K23: =SUM(K7:K22) -> 1289.8333 | L23: =SUM(L7:L22) -> 1083.3333 | N23: =SUM(N7:N22) -> 206.5 | O23: =SUM(O7:O22) -> 1289.8333 | P23: =SUM(P7:P22) -> 1083.3333 | R23: =SUM(R7:R22) -> 206.5 | S23: =SUM(S7:S22) -> 1289.8333 | T23: =SUM(T7:T22) -> 1083.3333 | V23: =SUM(V7:V22) -> 206.5 | W23: =SUM(W7:W22) -> 1289.8333 | X23: =SUM(X7:X22) -> 1083.3333 | Z23: =SUM(Z7:Z22) -> 206.5 | AA23: =SUM(AA7:AA22) -> 1289.8333 | AB23: =SUM(AB7:AB22) -> 1083.3333 | AD23: =SUM(AD7:AD22) -> 206.5 | AE23: =SUM(AE7:AE22) -> 1289.8333 | AF23: =SUM(AF7:AF22) -> 1083.3333 | AH23: =SUM(AH7:AH22) -> 206.5 | AI23: =SUM(AI7:AI22) -> 1289.8333 | AJ23: =SUM(AJ7:AJ22) -> 1083.3333 | AL23: =SUM(AL7:AL22) -> 206.5 | AM23: =SUM(AM7:AM22) -> 1289.8333 | AN23: =SUM(AN7:AN22) -> 1083.3333 | AP23: =SUM(AP7:AP22) -> 206.5 | AQ23: =SUM(AQ7:AQ22) -> 1289.8333 | AR23: =SUM(AR7:AR22) -> 1083.3333 | AT23: =SUM(AT7:AT22) -> 206.5 | AU23: =SUM(AU7:AU22) -> 1289.8333 | AV23: =SUM(AV7:AV22) -> 0 | AX23: =SUM(AX7:AX22) -> 0 | AY23: =SUM(AY7:AY22) -> 0
D26: MES 1 | H26: MES 2 | L26: MES 3 | P26: MES 4 | T26: MES 5 | X26: MES 6 | AB26: MES 7 | AF26: MES 8 | AJ26: MES 9 | AN26: MES 10 | AR26: MES 11 | AV26: MES 12
B27: GASTOS VARIABLES | C27: Imp Total S/IVA | D27: imp. Sin IVA | E27: % | F27: imp. IVA | G27: Total | H27: imp. Sin IVA | I27: % | J27: imp. IVA | K27: Total | L27: imp. Sin IVA | M27: % | N27: imp. IVA | O27: Total | P27: imp. Sin IVA | Q27: % | R27: imp. IVA | S27: Total | T27: imp. Sin IVA | U27: % | V27: imp. IVA | W27: Total | X27: imp. Sin IVA | Y27: % | Z27: imp. IVA | AA27: Total | AB27: imp. Sin IVA | AC27: % | AD27: imp. IVA | AE27: Total | AF27: imp. Sin IVA | AG27: % | AH27: imp. IVA | AI27: Total | AJ27: imp. Sin IVA | AK27: % | AL27: imp. IVA | AM27: Total | AN27: imp. Sin IVA | AO27: % | AP27: imp. IVA | AQ27: Total | AR27: imp. Sin IVA | AS27: % | AT27: imp. IVA | AU27: Total | AV27: imp. Sin IVA | AW27: % | AX27: imp. IVA | AY27: Total | AZ27: Salir Exacto
B28: Combustible | C28: 0 | D28: 0 | E28: 0.21 | F28: =D28*E28 -> 0 | G28: =D28+F28 -> 0 | H28: 0 | I28: 0.21 | J28: =H28*I28 -> 0 | K28: =H28+J28 -> 0 | L28: 0 | M28: 0.21 | N28: =L28*M28 -> 0 | O28: =L28+N28 -> 0 | P28: 0 | Q28: 0.21 | R28: =P28*Q28 -> 0 | S28: =P28+R28 -> 0 | T28: 0 | U28: 0.21 | V28: =T28*U28 -> 0 | W28: =T28+V28 -> 0 | X28: 0 | Y28: 0.21 | Z28: =X28*Y28 -> 0 | AA28: =X28+Z28 -> 0 | AB28: 0 | AC28: 0.21 | AD28: =AB28*AC28 -> 0 | AE28: =AB28+AD28 -> 0 | AF28: 0 | AG28: 0.21 | AH28: =AF28*AG28 -> 0 | AI28: =AF28+AH28 -> 0 | AJ28: 0 | AK28: 0.21 | AL28: =AJ28*AK28 -> 0 | AM28: =AJ28+AL28 -> 0 | AN28: 0 | AO28: 0.21 | AP28: =AN28*AO28 -> 0 | AQ28: =AN28+AP28 -> 0 | AR28: 0 | AS28: 0.21 | AT28: =AR28*AS28 -> 0 | AU28: =AR28+AT28 -> 0 | AV28: 0 | AW28: 0.21 | AX28: =AV28*AW28 -> 0 | AY28: =AV28+AX28 -> 0 | AZ28: =D28+H28+L28+P28+T28+X28+AB28+AF28+AJ28+AN28+AR28+AV28-C28 -> 0
B29: Materias Primas | C29: 0 | D29: 0 | E29: 0.21 | F29: =D29*E29 -> 0 | G29: =D29+F29 -> 0 | H29: 0 | I29: 0.21 | J29: =H29*I29 -> 0 | K29: =H29+J29 -> 0 | L29: 0 | M29: 0.21 | N29: =L29*M29 -> 0 | O29: =L29+N29 -> 0 | P29: 0 | Q29: 0.21 | R29: =P29*Q29 -> 0 | S29: =P29+R29 -> 0 | T29: 0 | U29: 0.21 | V29: =T29*U29 -> 0 | W29: =T29+V29 -> 0 | X29: 0 | Y29: 0.21 | Z29: =X29*Y29 -> 0 | AA29: =X29+Z29 -> 0 | AB29: 0 | AC29: 0.21 | AD29: =AB29*AC29 -> 0 | AE29: =AB29+AD29 -> 0 | AF29: 0 | AG29: 0.21 | AH29: =AF29*AG29 -> 0 | AI29: =AF29+AH29 -> 0 | AJ29: 0 | AK29: 0.21 | AL29: =AJ29*AK29 -> 0 | AM29: =AJ29+AL29 -> 0 | AN29: 0 | AO29: 0.21 | AP29: =AN29*AO29 -> 0 | AQ29: =AN29+AP29 -> 0 | AR29: 0 | AS29: 0.21 | AT29: =AR29*AS29 -> 0 | AU29: =AR29+AT29 -> 0 | AV29: 0 | AW29: 0.21 | AX29: =AV29*AW29 -> 0 | AY29: =AV29+AX29 -> 0 | AZ29: =D29+H29+L29+P29+T29+X29+AB29+AF29+AJ29+AN29+AR29+AV29-C29 -> 0
B30: Comisiones de prescripción / ventas (cooperativas y regantes) | C30: 1600 | D30: 133.33333 | E30: 0.21 | F30: =D30*E30 -> 28 | G30: =D30+F30 -> 161.33333 | H30: 133.33333 | I30: 0.21 | J30: =H30*I30 -> 28 | K30: =H30+J30 -> 161.33333 | L30: 133.33333 | M30: 0.21 | N30: =L30*M30 -> 28 | O30: =L30+N30 -> 161.33333 | P30: 133.33333 | Q30: 0.21 | R30: =P30*Q30 -> 28 | S30: =P30+R30 -> 161.33333 | T30: 133.33333 | U30: 0.21 | V30: =T30*U30 -> 28 | W30: =T30+V30 -> 161.33333 | X30: 133.33333 | Y30: 0.21 | Z30: =X30*Y30 -> 28 | AA30: =X30+Z30 -> 161.33333 | AB30: 133.33333 | AC30: 0.21 | AD30: =AB30*AC30 -> 28 | AE30: =AB30+AD30 -> 161.33333 | AF30: 133.33333 | AG30: 0.21 | AH30: =AF30*AG30 -> 28 | AI30: =AF30+AH30 -> 161.33333 | AJ30: 133.33333 | AK30: 0.21 | AL30: =AJ30*AK30 -> 28 | AM30: =AJ30+AL30 -> 161.33333 | AN30: 133.33333 | AO30: 0.21 | AP30: =AN30*AO30 -> 28 | AQ30: =AN30+AP30 -> 161.33333 | AR30: 133.33333 | AS30: 0.21 | AT30: =AR30*AS30 -> 28 | AU30: =AR30+AT30 -> 161.33333 | AV30: 0 | AW30: 0.21 | AX30: =AV30*AW30 -> 0 | AY30: =AV30+AX30 -> 0 | AZ30: =D30+H30+L30+P30+T30+X30+AB30+AF30+AJ30+AN30+AR30+AV30-C30 -> -133.33333
B31: Movilidad y transporte de campo | C31: 1200 | D31: 100 | E31: 0.21 | F31: =D31*E31 -> 21 | G31: =D31+F31 -> 121 | H31: 100 | I31: 0.21 | J31: =H31*I31 -> 21 | K31: =H31+J31 -> 121 | L31: 100 | M31: 0.21 | N31: =L31*M31 -> 21 | O31: =L31+N31 -> 121 | P31: 100 | Q31: 0.21 | R31: =P31*Q31 -> 21 | S31: =P31+R31 -> 121 | T31: 100 | U31: 0.21 | V31: =T31*U31 -> 21 | W31: =T31+V31 -> 121 | X31: 100 | Y31: 0.21 | Z31: =X31*Y31 -> 21 | AA31: =X31+Z31 -> 121 | AB31: 100 | AC31: 0.21 | AD31: =AB31*AC31 -> 21 | AE31: =AB31+AD31 -> 121 | AF31: 100 | AG31: 0.21 | AH31: =AF31*AG31 -> 21 | AI31: =AF31+AH31 -> 121 | AJ31: 100 | AK31: 0.21 | AL31: =AJ31*AK31 -> 21 | AM31: =AJ31+AL31 -> 121 | AN31: 100 | AO31: 0.21 | AP31: =AN31*AO31 -> 21 | AQ31: =AN31+AP31 -> 121 | AR31: 100 | AS31: 0.21 | AT31: =AR31*AS31 -> 21 | AU31: =AR31+AT31 -> 121 | AV31: 0 | AW31: 0.21 | AX31: =AV31*AW31 -> 0 | AY31: =AV31+AX31 -> 0 | AZ31: =D31+H31+L31+P31+T31+X31+AB31+AF31+AJ31+AN31+AR31+AV31-C31 -> -100
B32: Embalajes | C32: 0 | D32: 0 | E32: 0.21 | F32: =D32*E32 -> 0 | G32: =D32+F32 -> 0 | H32: 0 | I32: 0.21 | J32: =H32*I32 -> 0 | K32: =H32+J32 -> 0 | L32: 0 | M32: 0.21 | N32: =L32*M32 -> 0 | O32: =L32+N32 -> 0 | P32: 0 | Q32: 0.21 | R32: =P32*Q32 -> 0 | S32: =P32+R32 -> 0 | T32: 0 | U32: 0.21 | V32: =T32*U32 -> 0 | W32: =T32+V32 -> 0 | X32: 0 | Y32: 0.21 | Z32: =X32*Y32 -> 0 | AA32: =X32+Z32 -> 0 | AB32: 0 | AC32: 0.21 | AD32: =AB32*AC32 -> 0 | AE32: =AB32+AD32 -> 0 | AF32: 0 | AG32: 0.21 | AH32: =AF32*AG32 -> 0 | AI32: =AF32+AH32 -> 0 | AJ32: 0 | AK32: 0.21 | AL32: =AJ32*AK32 -> 0 | AM32: =AJ32+AL32 -> 0 | AN32: 0 | AO32: 0.21 | AP32: =AN32*AO32 -> 0 | AQ32: =AN32+AP32 -> 0 | AR32: 0 | AS32: 0.21 | AT32: =AR32*AS32 -> 0 | AU32: =AR32+AT32 -> 0 | AV32: 0 | AW32: 0.21 | AX32: =AV32*AW32 -> 0 | AY32: =AV32+AX32 -> 0 | AZ32: =D32+H32+L32+P32+T32+X32+AB32+AF32+AJ32+AN32+AR32+AV32-C32 -> 0
B33: … | C33: 0 | D33: 0 | E33: 0.21 | F33: =D33*E33 -> 0 | G33: =D33+F33 -> 0 | H33: 0 | I33: 0.21 | J33: =H33*I33 -> 0 | K33: =H33+J33 -> 0 | L33: 0 | M33: 0.21 | N33: =L33*M33 -> 0 | O33: =L33+N33 -> 0 | P33: 0 | Q33: 0.21 | R33: =P33*Q33 -> 0 | S33: =P33+R33 -> 0 | T33: 0 | U33: 0.21 | V33: =T33*U33 -> 0 | W33: =T33+V33 -> 0 | X33: 0 | Y33: 0.21 | Z33: =X33*Y33 -> 0 | AA33: =X33+Z33 -> 0 | AB33: 0 | AC33: 0.21 | AD33: =AB33*AC33 -> 0 | AE33: =AB33+AD33 -> 0 | AF33: 0 | AG33: 0.21 | AH33: =AF33*AG33 -> 0 | AI33: =AF33+AH33 -> 0 | AJ33: 0 | AK33: 0.21 | AL33: =AJ33*AK33 -> 0 | AM33: =AJ33+AL33 -> 0 | AN33: 0 | AO33: 0.21 | AP33: =AN33*AO33 -> 0 | AQ33: =AN33+AP33 -> 0 | AR33: 0 | AS33: 0.21 | AT33: =AR33*AS33 -> 0 | AU33: =AR33+AT33 -> 0 | AV33: 0 | AW33: 0.21 | AX33: =AV33*AW33 -> 0 | AY33: =AV33+AX33 -> 0 | AZ33: =D33+H33+L33+P33+T33+X33+AB33+AF33+AJ33+AN33+AR33+AV33-C33 -> 0
B34: … | C34: 0 | D34: 0 | E34: 0.21 | F34: =D34*E34 -> 0 | G34: =D34+F34 -> 0 | H34: 0 | I34: 0.21 | J34: =H34*I34 -> 0 | K34: =H34+J34 -> 0 | L34: 0 | M34: 0.21 | N34: =L34*M34 -> 0 | O34: =L34+N34 -> 0 | P34: 0 | Q34: 0.21 | R34: =P34*Q34 -> 0 | S34: =P34+R34 -> 0 | T34: 0 | U34: 0.21 | V34: =T34*U34 -> 0 | W34: =T34+V34 -> 0 | X34: 0 | Y34: 0.21 | Z34: =X34*Y34 -> 0 | AA34: =X34+Z34 -> 0 | AB34: 0 | AC34: 0.21 | AD34: =AB34*AC34 -> 0 | AE34: =AB34+AD34 -> 0 | AF34: 0 | AG34: 0.21 | AH34: =AF34*AG34 -> 0 | AI34: =AF34+AH34 -> 0 | AJ34: 0 | AK34: 0.21 | AL34: =AJ34*AK34 -> 0 | AM34: =AJ34+AL34 -> 0 | AN34: 0 | AO34: 0.21 | AP34: =AN34*AO34 -> 0 | AQ34: =AN34+AP34 -> 0 | AR34: 0 | AS34: 0.21 | AT34: =AR34*AS34 -> 0 | AU34: =AR34+AT34 -> 0 | AV34: 0 | AW34: 0.21 | AX34: =AV34*AW34 -> 0 | AY34: =AV34+AX34 -> 0 | AZ34: =D34+H34+L34+P34+T34+X34+AB34+AF34+AJ34+AN34+AR34+AV34-C34 -> 0
B35: … | C35: 0 | D35: 0 | E35: 0.21 | F35: =D35*E35 -> 0 | G35: =D35+F35 -> 0 | H35: 0 | I35: 0.21 | J35: =H35*I35 -> 0 | K35: =H35+J35 -> 0 | L35: 0 | M35: 0.21 | N35: =L35*M35 -> 0 | O35: =L35+N35 -> 0 | P35: 0 | Q35: 0.21 | R35: =P35*Q35 -> 0 | S35: =P35+R35 -> 0 | T35: 0 | U35: 0.21 | V35: =T35*U35 -> 0 | W35: =T35+V35 -> 0 | X35: 0 | Y35: 0.21 | Z35: =X35*Y35 -> 0 | AA35: =X35+Z35 -> 0 | AB35: 0 | AC35: 0.21 | AD35: =AB35*AC35 -> 0 | AE35: =AB35+AD35 -> 0 | AF35: 0 | AG35: 0.21 | AH35: =AF35*AG35 -> 0 | AI35: =AF35+AH35 -> 0 | AJ35: 0 | AK35: 0.21 | AL35: =AJ35*AK35 -> 0 | AM35: =AJ35+AL35 -> 0 | AN35: 0 | AO35: 0.21 | AP35: =AN35*AO35 -> 0 | AQ35: =AN35+AP35 -> 0 | AR35: 0 | AS35: 0.21 | AT35: =AR35*AS35 -> 0 | AU35: =AR35+AT35 -> 0 | AV35: 0 | AW35: 0.21 | AX35: =AV35*AW35 -> 0 | AY35: =AV35+AX35 -> 0 | AZ35: =D35+H35+L35+P35+T35+X35+AB35+AF35+AJ35+AN35+AR35+AV35-C35 -> 0
B36: … | C36: 0 | D36: 0 | E36: 0.21 | F36: =D36*E36 -> 0 | G36: =D36+F36 -> 0 | H36: 0 | I36: 0.21 | J36: =H36*I36 -> 0 | K36: =H36+J36 -> 0 | L36: 0 | M36: 0.21 | N36: =L36*M36 -> 0 | O36: =L36+N36 -> 0 | P36: 0 | Q36: 0.21 | R36: =P36*Q36 -> 0 | S36: =P36+R36 -> 0 | T36: 0 | U36: 0.21 | V36: =T36*U36 -> 0 | W36: =T36+V36 -> 0 | X36: 0 | Y36: 0.21 | Z36: =X36*Y36 -> 0 | AA36: =X36+Z36 -> 0 | AB36: 0 | AC36: 0.21 | AD36: =AB36*AC36 -> 0 | AE36: =AB36+AD36 -> 0 | AF36: 0 | AG36: 0.21 | AH36: =AF36*AG36 -> 0 | AI36: =AF36+AH36 -> 0 | AJ36: 0 | AK36: 0.21 | AL36: =AJ36*AK36 -> 0 | AM36: =AJ36+AL36 -> 0 | AN36: 0 | AO36: 0.21 | AP36: =AN36*AO36 -> 0 | AQ36: =AN36+AP36 -> 0 | AR36: 0 | AS36: 0.21 | AT36: =AR36*AS36 -> 0 | AU36: =AR36+AT36 -> 0 | AV36: 0 | AW36: 0.21 | AX36: =AV36*AW36 -> 0 | AY36: =AV36+AX36 -> 0 | AZ36: =D36+H36+L36+P36+T36+X36+AB36+AF36+AJ36+AN36+AR36+AV36-C36 -> 0
B37: … | C37: 0 | D37: 0 | E37: 0.21 | F37: =D37*E37 -> 0 | G37: =D37+F37 -> 0 | H37: 0 | I37: 0.21 | J37: =H37*I37 -> 0 | K37: =H37+J37 -> 0 | L37: 0 | M37: 0.21 | N37: =L37*M37 -> 0 | O37: =L37+N37 -> 0 | P37: 0 | Q37: 0.21 | R37: =P37*Q37 -> 0 | S37: =P37+R37 -> 0 | T37: 0 | U37: 0.21 | V37: =T37*U37 -> 0 | W37: =T37+V37 -> 0 | X37: 0 | Y37: 0.21 | Z37: =X37*Y37 -> 0 | AA37: =X37+Z37 -> 0 | AB37: 0 | AC37: 0.21 | AD37: =AB37*AC37 -> 0 | AE37: =AB37+AD37 -> 0 | AF37: 0 | AG37: 0.21 | AH37: =AF37*AG37 -> 0 | AI37: =AF37+AH37 -> 0 | AJ37: 0 | AK37: 0.21 | AL37: =AJ37*AK37 -> 0 | AM37: =AJ37+AL37 -> 0 | AN37: 0 | AO37: 0.21 | AP37: =AN37*AO37 -> 0 | AQ37: =AN37+AP37 -> 0 | AR37: 0 | AS37: 0.21 | AT37: =AR37*AS37 -> 0 | AU37: =AR37+AT37 -> 0 | AV37: 0 | AW37: 0.21 | AX37: =AV37*AW37 -> 0 | AY37: =AV37+AX37 -> 0 | AZ37: =D37+H37+L37+P37+T37+X37+AB37+AF37+AJ37+AN37+AR37+AV37-C37 -> 0
B38: … | C38: 0 | D38: 0 | E38: 0.21 | F38: =D38*E38 -> 0 | G38: =D38+F38 -> 0 | H38: 0 | I38: 0.21 | J38: =H38*I38 -> 0 | K38: =H38+J38 -> 0 | L38: 0 | M38: 0.21 | N38: =L38*M38 -> 0 | O38: =L38+N38 -> 0 | P38: 0 | Q38: 0.21 | R38: =P38*Q38 -> 0 | S38: =P38+R38 -> 0 | T38: 0 | U38: 0.21 | V38: =T38*U38 -> 0 | W38: =T38+V38 -> 0 | X38: 0 | Y38: 0.21 | Z38: =X38*Y38 -> 0 | AA38: =X38+Z38 -> 0 | AB38: 0 | AC38: 0.21 | AD38: =AB38*AC38 -> 0 | AE38: =AB38+AD38 -> 0 | AF38: 0 | AG38: 0.21 | AH38: =AF38*AG38 -> 0 | AI38: =AF38+AH38 -> 0 | AJ38: 0 | AK38: 0.21 | AL38: =AJ38*AK38 -> 0 | AM38: =AJ38+AL38 -> 0 | AN38: 0 | AO38: 0.21 | AP38: =AN38*AO38 -> 0 | AQ38: =AN38+AP38 -> 0 | AR38: 0 | AS38: 0.21 | AT38: =AR38*AS38 -> 0 | AU38: =AR38+AT38 -> 0 | AV38: 0 | AW38: 0.21 | AX38: =AV38*AW38 -> 0 | AY38: =AV38+AX38 -> 0 | AZ38: =D38+H38+L38+P38+T38+X38+AB38+AF38+AJ38+AN38+AR38+AV38-C38 -> 0
B39: … | C39: 0 | D39: 0 | E39: 0.21 | F39: =D39*E39 -> 0 | G39: =D39+F39 -> 0 | H39: 0 | I39: 0.21 | J39: =H39*I39 -> 0 | K39: =H39+J39 -> 0 | L39: 0 | M39: 0.21 | N39: =L39*M39 -> 0 | O39: =L39+N39 -> 0 | P39: 0 | Q39: 0.21 | R39: =P39*Q39 -> 0 | S39: =P39+R39 -> 0 | T39: 0 | U39: 0.21 | V39: =T39*U39 -> 0 | W39: =T39+V39 -> 0 | X39: 0 | Y39: 0.21 | Z39: =X39*Y39 -> 0 | AA39: =X39+Z39 -> 0 | AB39: 0 | AC39: 0.21 | AD39: =AB39*AC39 -> 0 | AE39: =AB39+AD39 -> 0 | AF39: 0 | AG39: 0.21 | AH39: =AF39*AG39 -> 0 | AI39: =AF39+AH39 -> 0 | AJ39: 0 | AK39: 0.21 | AL39: =AJ39*AK39 -> 0 | AM39: =AJ39+AL39 -> 0 | AN39: 0 | AO39: 0.21 | AP39: =AN39*AO39 -> 0 | AQ39: =AN39+AP39 -> 0 | AR39: 0 | AS39: 0.21 | AT39: =AR39*AS39 -> 0 | AU39: =AR39+AT39 -> 0 | AV39: 0 | AW39: 0.21 | AX39: =AV39*AW39 -> 0 | AY39: =AV39+AX39 -> 0 | AZ39: =D39+H39+L39+P39+T39+X39+AB39+AF39+AJ39+AN39+AR39+AV39-C39 -> 0
... B42: … | C42: 0 | D42: 0 | E42: 0.21 | F42: =D42*E42 -> 0 | G42: =D42+F42 -> 0 | H42: 0 | I42: 0.21 | J42: =H42*I42 -> 0 | K42: =H42+J42 -> 0 | L42: 0 | M42: 0.21 | N42: =L42*M42 -> 0 | O42: =L42+N42 -> 0 | P42: 0 | Q42: 0.21 | R42: =P42*Q42 -> 0 | S42: =P42+R42 -> 0 | T42: 0 | U42: 0.21 | V42: =T42*U42 -> 0 | W42: =T42+V42 -> 0 | X42: 0 | Y42: 0.21 | Z42: =X42*Y42 -> 0 | AA42: =X42+Z42 -> 0 | AB42: 0 | AC42: 0.21 | AD42: =AB42*AC42 -> 0 | AE42: =AB42+AD42 -> 0 | AF42: 0 | AG42: 0.21 | AH42: =AF42*AG42 -> 0 | AI42: =AF42+AH42 -> 0 | AJ42: 0 | AK42: 0.21 | AL42: =AJ42*AK42 -> 0 | AM42: =AJ42+AL42 -> 0 | AN42: 0 | AO42: 0.21 | AP42: =AN42*AO42 -> 0 | AQ42: =AN42+AP42 -> 0 | AR42: 0 | AS42: 0.21 | AT42: =AR42*AS42 -> 0 | AU42: =AR42+AT42 -> 0 | AV42: 0 | AW42: 0.21 | AX42: =AV42*AW42 -> 0 | AY42: =AV42+AX42 -> 0 | AZ42: =D42+H42+L42+P42+T42+X42+AB42+AF42+AJ42+AN42+AR42+AV42-C42 -> 0
B43: TOTAL DE GASTOS VARIABLES | C43: =SUM(C28:C42) -> 2800 | D43: =SUM(D28:D42) -> 233.33333 | F43: =SUM(F28:F42) -> 49 | G43: =SUM(G28:G42) -> 282.33333 | H43: =SUM(H28:H42) -> 233.33333 | J43: =SUM(J28:J42) -> 49 | K43: =SUM(K28:K42) -> 282.33333 | L43: =SUM(L28:L42) -> 233.33333 | N43: =SUM(N28:N42) -> 49 | O43: =SUM(O28:O42) -> 282.33333 | P43: =SUM(P28:P42) -> 233.33333 | R43: =SUM(R28:R42) -> 49 | S43: =SUM(S28:S42) -> 282.33333 | T43: =SUM(T28:T42) -> 233.33333 | V43: =SUM(V28:V42) -> 49 | W43: =SUM(W28:W42) -> 282.33333 | X43: =SUM(X28:X42) -> 233.33333 | Z43: =SUM(Z28:Z42) -> 49 | AA43: =SUM(AA28:AA42) -> 282.33333 | AB43: =SUM(AB28:AB42) -> 233.33333 | AD43: =SUM(AD28:AD42) -> 49 | AE43: =SUM(AE28:AE42) -> 282.33333 | AF43: =SUM(AF28:AF42) -> 233.33333 | AH43: =SUM(AH28:AH42) -> 49 | AI43: =SUM(AI28:AI42) -> 282.33333 | AJ43: =SUM(AJ28:AJ42) -> 233.33333 | AL43: =SUM(AL28:AL42) -> 49 | AM43: =SUM(AM28:AM42) -> 282.33333 | AN43: =SUM(AN28:AN42) -> 233.33333 | AP43: =SUM(AP28:AP42) -> 49 | AQ43: =SUM(AQ28:AQ42) -> 282.33333 | AR43: =SUM(AR28:AR42) -> 233.33333 | AT43: =SUM(AT28:AT42) -> 49 | AU43: =SUM(AU28:AU42) -> 282.33333 | AV43: =SUM(AV28:AV42) -> 0 | AX43: =SUM(AX28:AX42) -> 0 | AY43: =SUM(AY28:AY42) -> 0 | AZ43: =D44+H44+L44+P44+T44+X44+AB44+AF44+AJ44+AN44+AR44+AV44-C44 -> 0
B46: TOTAL IMPORTE GASTOS FIJOS CON IVA | D46: =G23+K23+O23+S23+W23+AA23+AE23+AI23+AM23+AQ23+AU23+AY23 -> 14188.167
B47: TOTAL IMPORTE GASTOS VARIABLES CON IVA | D47: =G43+K43+O43+S43+W43+AA43+AE43+AI43+AM43+AQ43+AU43+AY43 -> 3105.6667
A49: CAC/LTV: marketing fijo 4.000 €/año; comisiones de prescripción 1.600 €/año; movilidad 1.200 €/año. La comisión de prescripción se calcula como incentivo por piloto/cliente referido y se activa con contrato o factura.

Sheet Gastos de Personal
B3: Gastos de Personal
B5: PERSONAL 1 — Promotor / dirección técnica (30.000 € + RETA 4.800 €) | C5: MES 1 | D5: MES 2 | E5: MES 3 | F5: MES 4 | G5: MES 5 | H5: MES 6 | I5: MES 7 | J5: MES 8 | K5: MES 9 | L5: MES 10 | M5: MES 11 | N5: MES 12 | O5: TOTAL ANUAL
B6: Salario Bruto | C6: 2500 | D6: 2500 | E6: 2500 | F6: 2500 | G6: 2500 | H6: 2500 | I6: 2500 | J6: 2500 | K6: 2500 | L6: 2500 | M6: 2500 | N6: 2500 | O6: =SUM(C6:N6) -> 30000
B7: S.Soc. Empr (%) | C7: 0.16 | D7: 0.16 | E7: 0.16 | F7: 0.16 | G7: 0.16 | H7: 0.16 | I7: 0.16 | J7: 0.16 | K7: 0.16 | L7: 0.16 | M7: 0.16 | N7: 0.16 | O7: =O6*C7 -> 4800
B8: Coste Total | C8: =C6+C6*C7 -> 2900 | D8: =D6+D6*D7 -> 2900 | E8: =E6+E6*E7 -> 2900 | F8: =F6+F6*F7 -> 2900 | G8: =G6+G6*G7 -> 2900 | H8: =H6+H6*H7 -> 2900 | I8: =I6+I6*I7 -> 2900 | J8: =J6+J6*J7 -> 2900 | ... N8: =N6+N6*N7 -> 2900 | O8: =SUM(C8:N8) -> 34800
B10: PERSONAL 2 — Técnico/a de software (activación meses 6–10) | C10: MES 1 | D10: MES 2 | E10: MES 3 | F10: MES 4 | G10: MES 5 | H10: MES 6 | I10: MES 7 | J10: MES 8 | K10: MES 9 | L10: MES 10 | M10: MES 11 | N10: MES 12 | O10: TOTAL ANUAL
B11: Salario Bruto | C11: 0 | D11: 0 | E11: 0 | F11: 0 | G11: 0 | H11: 2333.3333 | I11: 2333.3333 | J11: 2333.3333 | K11: 2333.3333 | L11: 2333.3333 | M11: 0 | N11: 0 | O11: =SUM(C11:N11) -> 11666.667
B12: S.Soc. Empr (%) | C12: 0 | D12: 0 | E12: 0 | F12: 0 | G12: 0 | H12: 0.3 | I12: 0.3 | J12: 0.3 | K12: 0.3 | L12: 0.3 | M12: 0 | N12: 0 | O12: =O11*C12 -> 0
B13: Coste Total | C13: =C11+(C11*C12) -> 0 | D13: =D11+(D11*D12) -> 0 | E13: =E11+(E11*E12) -> 0 | F13: =F11+(F11*F12) -> 0 | G13: =G11+(G11*G12) -> 0 | H13: =H11+(H11*H12) -> 3033.3333 | I13: =I11+(I11*I12) -> 3033.3333 | J13: =J11+(J11*J12) -> 3033.3333 | ... N13: =N11+(N11*N12) -> 0 | O13: =SUM(C13:N13) -> 15166.667
B15: PERSONAL 3 — Técnico/a de campo/comercial (activación meses 11–12) | C15: MES 1 | D15: MES 2 | E15: MES 3 | F15: MES 4 | G15: MES 5 | H15: MES 6 | I15: MES 7 | J15: MES 8 | K15: MES 9 | L15: MES 10 | M15: MES 11 | N15: MES 12 | O15: TOTAL ANUAL
B16: Salario Bruto | C16: 0 | D16: 0 | E16: 0 | F16: 0 | G16: 0 | H16: 0 | I16: 0 | J16: 0 | K16: 0 | L16: 0 | M16: 1000 | N16: 1000 | O16: =SUM(C16:N16) -> 2000
B17: S.Soc. Empr (%) | C17: 0 | D17: 0 | E17: 0 | F17: 0 | G17: 0 | H17: 0 | I17: 0 | J17: 0 | K17: 0 | L17: 0 | M17: 0.3 | N17: 0.3 | O17: =O16*C17 -> 0
B18: Coste Total | C18: =C16+(C16*C17) -> 0 | D18: =D16+(D16*D17) -> 0 | E18: =E16+(E16*E17) -> 0 | F18: =F16+(F16*F17) -> 0 | G18: =G16+(G16*G17) -> 0 | H18: =H16+(H16*H17) -> 0 | I18: =I16+(I16*I17) -> 0 | J18: =J16+(J16*J17) -> 0 | ... N18: =N16+(N16*N17) -> 1300 | O18: =SUM(C18:N18) -> 2600
B20: PERSONAL 4 | C20: MES 1 | D20: MES 2 | E20: MES 3 | F20: MES 4 | G20: MES 5 | H20: MES 6 | I20: MES 7 | J20: MES 8 | K20: MES 9 | L20: MES 10 | M20: MES 11 | N20: MES 12 | O20: TOTAL ANUAL
B21: Salario Bruto | C21: 0 | D21: 0 | E21: 0 | F21: 0 | G21: 0 | H21: 0 | I21: 0 | J21: 0 | K21: 0 | L21: 0 | M21: 0 | N21: 0 | O21: =SUM(C21:N21) -> 0
B22: S.Soc. Empr (%) | C22: 0 | D22: 0 | E22: 0 | F22: 0 | G22: 0 | H22: 0 | I22: 0 | J22: 0 | K22: 0 | L22: 0 | M22: 0 | N22: 0 | O22: =O21*C22 -> 0
B23: Coste Total | C23: =C21+(C21*C22) -> 0 | D23: =D21+(D21*D22) -> 0 | E23: =E21+(E21*E22) -> 0 | F23: =F21+(F21*F22) -> 0 | G23: =G21+(G21*G22) -> 0 | H23: =H21+(H21*H22) -> 0 | I23: =I21+(I21*I22) -> 0 | J23: =J21+(J21*J22) -> 0 | ... N23: =N21+(N21*N22) -> 0 | O23: =SUM(C23:N23) -> 0
B25: PERSONAL 5 | C25: MES 1 | D25: MES 2 | E25: MES 3 | F25: MES 4 | G25: MES 5 | H25: MES 6 | I25: MES 7 | J25: MES 8 | K25: MES 9 | L25: MES 10 | M25: MES 11 | N25: MES 12 | O25: TOTAL ANUAL
B26: Salario Bruto | C26: 0 | D26: 0 | E26: 0 | F26: 0 | G26: 0 | H26: 0 | I26: 0 | J26: 0 | K26: 0 | L26: 0 | M26: 0 | N26: 0 | O26: =SUM(C26:N26) -> 0
B27: S.Soc. Empr (%) | C27: 0 | D27: 0 | E27: 0 | F27: 0 | G27: 0 | H27: 0 | I27: 0 | J27: 0 | K27: 0 | L27: 0 | M27: 0 | N27: 0 | O27: =O26*C27 -> 0
B28: Coste Total | C28: =C26+(C26*C27) -> 0 | D28: =D26+(D26*D27) -> 0 | E28: =E26+(E26*E27) -> 0 | F28: =F26+(F26*F27) -> 0 | G28: =G26+(G26*G27) -> 0 | H28: =H26+(H26*H27) -> 0 | I28: =I26+(I26*I27) -> 0 | J28: =J26+(J26*J27) -> 0 | ... N28: =N26+(N26*N27) -> 0 | O28: =SUM(C28:N28) -> 0
B31: TOTAL GASTO DE PERSONAL | C31: MES 1 | D31: MES 2 | E31: MES 3 | F31: MES 4 | G31: MES 5 | H31: MES 6 | I31: MES 7 | J31: MES 8 | K31: MES 9 | L31: MES 10 | M31: MES 11 | N31: MES 12 | O31: TOTAL ANUAL
C32: =C8+C13+C18+C23+C28 -> 2900 | D32: =D8+D13+D18+D23+D28 -> 2900 | E32: =E8+E13+E18+E23+E28 -> 2900 | F32: =F8+F13+F18+F23+F28 -> 2900 | G32: =G8+G13+G18+G23+G28 -> 2900 | H32: =H8+H13+H18+H23+H28 -> 5933.3333 | I32: =I8+I13+I18+I23+I28 -> 5933.3333 | J32: =J8+J13+J18+J23+J28 -> 5933.3333 | ... N32: =N8+N13+N18+N23+N28 -> 4200 | O32: =SUM(C32:N32) -> 52566.667
A34: Personal escalonado: promotor 30.000 € brutos + RETA presupuestado; software desde la activación; campo/comercial desde pilotos. No se contabilizan perfiles futuros hasta Gates.
A35: FUENTE ÚNICA DE PERSONAL — DEBE COINCIDIR CON LA MEMORIA
A36: Promotor / dirección técnica | B36: 30.000,00 € bruto + 4.800,00 € RETA | C36: F1 | D36: Planificado
A37: Técnico/a de software | B37: 15.166,67 € reconocido en meses 6–10 | C37: F1 | D37: Planificado
A38: Técnico/a de campo/comercial | B38: 2.600,00 € reconocido en meses 11–12 | C38: F1 | D38: Condicionado
A39: TOTAL PERSONAL RECONOCIDO AÑO 1 | B39: 52.566,67 € | C39: Año 1 | D39: Fuente oficial
A40: La memoria no debe presentar una anualización teórica distinta: el Excel oficial reconoce 52.566,67 € en Año 1 según meses efectivos de contratación.
A41: DISTINCIÓN OBLIGATORIA: CAPACIDAD ANUALIZADA VS. COSTE RECONOCIDO
A42: Capacidad humana anualizada de referencia: 86.800,00 € (30.000 + 4.800 RETA + 28.000 + 8.400 SS + 12.000 + 3.600 SS). No es el gasto P&L del Año 1.
A43: Coste reconocido P&L Año 1: 52.566,67 €, según meses efectivos del calendario oficial. No existe contradicción: son magnitudes con distinto perímetro.

Sheet Amortización Contable
B2: Amortización Contable
B4: Tipología | C4: Precio de adquisión | D4: IVA | E4: Coeficiente lineal (*) | F4: Cuota anual
B5: Gastos de I+D | C5: ='Inversión Inicial'!C19+'Inversión Inicial'!E19+'Inversión Inicial'!H19 -> 30000 | D5: 0.21 | E5: 0.2 | F5: =C5*E5 -> 6000
B6: Patentes, Modelos de Utilidad | C6: ='Inversión Inicial'!C20+'Inversión Inicial'!E20+'Inversión Inicial'!H20 -> 0 | D6: 0.21 | E6: 0.1 | F6: =C6*E6 -> 0
B7: Aplicaciones informáticas | C7: ='Inversión Inicial'!C21+'Inversión Inicial'!E21+'Inversión Inicial'!H21 -> 47250 | D7: 0.21 | E7: 0.1 | F7: =C7*E7 -> 4725
B8: Derechos de traspaso | C8: ='Inversión Inicial'!C22+'Inversión Inicial'!E22+'Inversión Inicial'!H22 -> 0 | D8: 0 | E8: 0 | F8: =C8*E8 -> 0
B9: Fondo de comercio | C9: ='Inversión Inicial'!C25+'Inversión Inicial'!E25+'Inversión Inicial'!H25 -> 0 | D9: 0 | E9: 0.05 | F9: =C9*E9 -> 0
B10: Marca, Nombre Comercial | C10: ='Inversión Inicial'!C23+'Inversión Inicial'!E23+'Inversión Inicial'!H23 -> 210.72 | D10: 0 | E10: 0.1 | F10: =C10*E10 -> 21.072
B11: Otros (...) | C11: ='Inversión Inicial'!C24+'Inversión Inicial'!E24+'Inversión Inicial'!H24 -> 5000 | D11: 0.21 | E11: 0 | F11: =C11*E11 -> 0
B12: TOTAL AMORT. INMOV. INMATERIAL | F12: =SUM(F5:F11) -> 10746.072
B14: Tipología | C14: Precio de adquisión | D14: IVA | E14: Coeficiente lineal (*) | F14: Cuota anual
B15: Edificios y Construcciones | C15: ='Inversión Inicial'!C7+'Inversión Inicial'!E7+'Inversión Inicial'!H7 -> 0 | D15: 0.21 | E15: 0.03 | F15: =C15*E15 -> 0
B16: Instalaciones | C16: ='Inversión Inicial'!C8+'Inversión Inicial'!E8+'Inversión Inicial'!H8 -> 0 | D16: 0.21 | E16: 0.1 | F16: =C16*E16 -> 0
B17: Maquinaria | C17: ='Inversión Inicial'!C9+'Inversión Inicial'!E9+'Inversión Inicial'!H9 -> 0 | D17: 0.21 | E17: 0.12 | F17: =C17*E17 -> 0
B18: Equipamiento | C18: ='Inversión Inicial'!C10+'Inversión Inicial'!E10+'Inversión Inicial'!H10 -> 0 | D18: 0.21 | E18: 0.1 | F18: =C18*E18 -> 0
B19: Mobiliario | C19: ='Inversión Inicial'!C11+'Inversión Inicial'!E11+'Inversión Inicial'!H11 -> 0 | D19: 0.21 | E19: 0.1 | F19: =C19*E19 -> 0
B20: Utillaje | C20: ='Inversión Inicial'!C12+'Inversión Inicial'!E12+'Inversión Inicial'!H12 -> 0 | D20: 0.21 | E20: 0.3 | F20: =C20*E20 -> 0
B21: Vehículos de transporte | C21: ='Inversión Inicial'!C13+'Inversión Inicial'!E13+'Inversión Inicial'!H13 -> 0 | D21: 0.21 | E21: 0.16 | F21: =C21*E21 -> 0
B22: Equipos informáticos | C22: ='Inversión Inicial'!C14+'Inversión Inicial'!E14+'Inversión Inicial'!H14 -> 0 | D22: 0.21 | E22: 0.26 | F22: =C22*E22 -> 0
B23: Otros (proyectos técnicos...) | C23: ='Inversión Inicial'!C15+'Inversión Inicial'!E15+'Inversión Inicial'!H15 -> 10000 | D23: 0.21 | E23: 0.1 | F23: =C23*E23 -> 1000
B24: TOTAL AMORT. INMOV. MATERIAL | F24: =SUM(F15:F23) -> 1000
B26: Esta información se obtiene de manera automática, teniendo en cuenta datos que se han introducido en apartados anteriores.
B27: La cuota anual de amortización se lleva a la Cuenta de Resultados y la amortización acumulada al Balance de situación.
B28: Coeficiente lineal (*), se puede cambiar el %.

Sheet Flujo de Caja
A1: ESCENARIO PROFORMA CONDICIONADO: 180.000 € se muestra en flujo solo para simular la ejecución tras concesión y desembolso. La situación documental real mantiene financiación cobrada = 0 € y caja propia inicial = 0 €.
C3: Flujo de Caja
D5: Arranque | E5: MES 1 | F5: MES 2 | G5: MES 3 | H5: MES 4 | I5: MES 5 | J5: MES 6 | K5: MES 7 | L5: MES 8 | M5: MES 9 | N5: MES 10 | O5: MES 11 | P5: MES 12
B6: Cobros de las ventas | E6: =('Costes produción y ventas'!E13*'Costes produción y ventas'!H21)+('Costes produción y ventas'!E14*'Costes produción y ventas'!H29)+('Costes produción y ventas'!E15*'Costes produción y ventas'!H37)+('Costes produción y ventas'!E16*'Costes produción y ventas'!H45)+('Costes produción y ventas'!E17*'Costes produción y ventas'!H53) -> 0 | F6: =('Costes produción y ventas'!E13*'Costes produción y ventas'!I21)+('Costes produción y ventas'!E14*'Costes produción y ventas'!I29)+('Costes produción y ventas'!E15*'Costes produción y ventas'!I37)+('Costes produción y ventas'!E16*'Costes produción y ventas'!I45)+('Costes produción y ventas'!E17*'Costes produción y ventas'!I53) -> 0 | G6: =('Costes produción y ventas'!E13*'Costes produción y ventas'!J21)+('Costes produción y ventas'!E14*'Costes produción y ventas'!J29)+('Costes produción y ventas'!E15*'Costes produción y ventas'!J37)+('Costes produción y ventas'!E16*'Costes produción y ventas'!J45)+('Costes produción y ventas'!E17*'Costes produción y ventas'!J53) -> 605 | H6: =('Costes produción y ventas'!E13*'Costes produción y ventas'!K21)+('Costes produción y ventas'!E14*'Costes produción y ventas'!K29)+('Costes produción y ventas'!E15*'Costes produción y ventas'!K37)+('Costes produción y ventas'!E16*'Costes produción y ventas'!K45)+('Costes produción y ventas'!E17*'Costes produción y ventas'!K53) -> 1512.5 | I6: =('Costes produción y ventas'!E13*'Costes produción y ventas'!L21)+('Costes produción y ventas'!E14*'Costes produción y ventas'!L29)+('Costes produción y ventas'!E15*'Costes produción y ventas'!L37)+('Costes produción y ventas'!E16*'Costes produción y ventas'!L45)+('Costes produción y ventas'!E17*'Costes produción y ventas'!L53) -> 1815 | J6: =('Costes produción y ventas'!E13*'Costes produción y ventas'!M21)+('Costes produción y ventas'!E14*'Costes produción y ventas'!M29)+('Costes produción y ventas'!E15*'Costes produción y ventas'!M37)+('Costes produción y ventas'!E16*'Costes produción y ventas'!M45)+('Costes produción y ventas'!E17*'Costes produción y ventas'!M53) -> 3932.5 | K6: =('Costes produción y ventas'!E13*'Costes produción y ventas'!N21)+('Costes produción y ventas'!E14*'Costes produción y ventas'!N29)+('Costes produción y ventas'!E15*'Costes produción y ventas'!N37)+('Costes produción y ventas'!E16*'Costes produción y ventas'!N45)+('Costes produción y ventas'!E17*'Costes produción y ventas'!N53) -> 5687 | L6: =('Costes produción y ventas'!E13*'Costes produción y ventas'!O21)+('Costes produción y ventas'!E14*'Costes produción y ventas'!O29)+('Costes produción y ventas'!E15*'Costes produción y ventas'!O37)+('Costes produción y ventas'!E16*'Costes produción y ventas'!O45)+('Costes produción y ventas'!E17*'Costes produción y ventas'!O53) -> 7401.1667 | M6: =('Costes produción y ventas'!E13*'Costes produción y ventas'!P21)+('Costes produción y ventas'!E14*'Costes produción y ventas'!P29)+('Costes produción y ventas'!E15*'Costes produción y ventas'!P37)+('Costes produción y ventas'!E16*'Costes produción y ventas'!P45)+('Costes produción y ventas'!E17*'Costes produción y ventas'!P53) -> 7703.6667 | N6: =('Costes produción y ventas'!E13*'Costes produción y ventas'!Q21)+('Costes produción y ventas'!E14*'Costes produción y ventas'!Q29)+('Costes produción y ventas'!E15*'Costes produción y ventas'!Q37)+('Costes produción y ventas'!E16*'Costes produción y ventas'!Q45)+('Costes produción y ventas'!E17*'Costes produción y ventas'!Q53) -> 8006.1667 | O6: =('Costes produción y ventas'!E13*'Costes produción y ventas'!R21)+('Costes produción y ventas'!E14*'Costes produción y ventas'!R29)+('Costes produción y ventas'!E15*'Costes produción y ventas'!R37)+('Costes produción y ventas'!E16*'Costes produción y ventas'!R45)+('Costes produción y ventas'!E17*'Costes produción y ventas'!R53) -> 5989.5 | P6: =('Costes produción y ventas'!E13*'Costes produción y ventas'!S21)+('Costes produción y ventas'!E14*'Costes produción y ventas'!S29)+('Costes produción y ventas'!E15*'Costes produción y ventas'!S37)+('Costes produción y ventas'!E16*'Costes produción y ventas'!S45)+('Costes produción y ventas'!E17*'Costes produción y ventas'!S53) -> 5142.5
B7: Otros
B8: Recursos Propios | D8: 0
B9: Financiación externa central F1 — escenario proforma condicionado a concesión y desembolso | D9: 180000
B11: Total de Cobros | D11: =D8+D9 -> 180000 | E11: =SUM(E6:E7) -> 0 | F11: =SUM(F6:F7) -> 0 | G11: =SUM(G6:G7) -> 605 | H11: =SUM(H6:H7) -> 1512.5 | I11: =SUM(I6:I7) -> 1815 | J11: =SUM(J6:J7) -> 3932.5 | K11: =SUM(K6:K7) -> 5687 | L11: =SUM(L6:L7) -> 7401.1667 | ... P11: =SUM(P6:P7) -> 5142.5
B12: Pago de Sueldos | E12: ='Gastos de Personal'!C32 -> 2900 | F12: ='Gastos de Personal'!D32 -> 2900 | G12: ='Gastos de Personal'!E32 -> 2900 | H12: ='Gastos de Personal'!F32 -> 2900 | I12: ='Gastos de Personal'!G32 -> 2900 | J12: ='Gastos de Personal'!H32 -> 5933.3333 | K12: ='Gastos de Personal'!I32 -> 5933.3333 | L12: ='Gastos de Personal'!J32 -> 5933.3333 | ... P12: ='Gastos de Personal'!N32 -> 4200
B13: Pago compras y gastos generales | E13: =('Costes produción y ventas'!E4*'Costes produción y ventas'!H21)+('Costes produción y ventas'!E5*'Costes produción y ventas'!H29)+('Costes produción y ventas'!E6*'Costes produción y ventas'!H37)+('Costes produción y ventas'!E7*'Costes produción y ventas'!H45)+('Costes produción y ventas'!E8*'Costes produción y ventas'!H53)+'Gasto Fijos y Variables'!G23+'Gasto Fijos y Variables'!G43 -> 1572.1667 | F13: =('Costes produción y ventas'!E4*'Costes produción y ventas'!I21)+('Costes produción y ventas'!E5*'Costes produción y ventas'!I29)+('Costes produción y ventas'!E6*'Costes produción y ventas'!I37)+('Costes produción y ventas'!E7*'Costes produción y ventas'!I45)+('Costes produción y ventas'!E8*'Costes produción y ventas'!I53)+'Gasto Fijos y Variables'!K23+'Gasto Fijos y Variables'!K43 -> 1572.1667 | G13: =('Costes produción y ventas'!E4*'Costes produción y ventas'!J21)+('Costes produción y ventas'!E5*'Costes produción y ventas'!J29)+('Costes produción y ventas'!E6*'Costes produción y ventas'!J37)+('Costes produción y ventas'!E7*'Costes produción y ventas'!J45)+('Costes produción y ventas'!E8*'Costes produción y ventas'!J53)+'Gasto Fijos y Variables'!O23+'Gasto Fijos y Variables'!O43 -> 1729.4667 | H13: =('Costes produción y ventas'!E4*'Costes produción y ventas'!K21)+('Costes produción y ventas'!E5*'Costes produción y ventas'!K29)+('Costes produción y ventas'!E6*'Costes produción y ventas'!K37)+('Costes produción y ventas'!E7*'Costes produción y ventas'!K45)+('Costes produción y ventas'!E8*'Costes produción y ventas'!K53)+'Gasto Fijos y Variables'!S23+'Gasto Fijos y Variables'!S43 -> 1989.6167 | I13: =('Costes produción y ventas'!E4*'Costes produción y ventas'!L21)+('Costes produción y ventas'!E5*'Costes produción y ventas'!L29)+('Costes produción y ventas'!E6*'Costes produción y ventas'!L37)+('Costes produción y ventas'!E7*'Costes produción y ventas'!L45)+('Costes produción y ventas'!E8*'Costes produción y ventas'!L53)+'Gasto Fijos y Variables'!W23+'Gasto Fijos y Variables'!W43 -> 2068.2667 | J13: =('Costes produción y ventas'!E4*'Costes produción y ventas'!M21)+('Costes produción y ventas'!E5*'Costes produción y ventas'!M29)+('Costes produción y ventas'!E6*'Costes produción y ventas'!M37)+('Costes produción y ventas'!E7*'Costes produción y ventas'!M45)+('Costes produción y ventas'!E8*'Costes produción y ventas'!M53)+'Gasto Fijos y Variables'!AA23+'Gasto Fijos y Variables'!AA43 -> 2509.9167 | K13: =('Costes produción y ventas'!E4*'Costes produción y ventas'!N21)+('Costes produción y ventas'!E5*'Costes produción y ventas'!N29)+('Costes produción y ventas'!E6*'Costes produción y ventas'!N37)+('Costes produción y ventas'!E7*'Costes produción y ventas'!N45)+('Costes produción y ventas'!E8*'Costes produción y ventas'!N53)+'Gasto Fijos y Variables'!AE23+'Gasto Fijos y Variables'!AE43 -> 3072.5667 | L13: =('Costes produción y ventas'!E4*'Costes produción y ventas'!O21)+('Costes produción y ventas'!E5*'Costes produción y ventas'!O29)+('Costes produción y ventas'!E6*'Costes produción y ventas'!O37)+('Costes produción y ventas'!E7*'Costes produción y ventas'!O45)+('Costes produción y ventas'!E8*'Costes produción y ventas'!O53)+'Gasto Fijos y Variables'!AI23+'Gasto Fijos y Variables'!AI43 -> 3624.9317 | M13: =('Costes produción y ventas'!E4*'Costes produción y ventas'!P21)+('Costes produción y ventas'!E5*'Costes produción y ventas'!P29)+('Costes produción y ventas'!E6*'Costes produción y ventas'!P37)+('Costes produción y ventas'!E7*'Costes produción y ventas'!P45)+('Costes produción y ventas'!E8*'Costes produción y ventas'!P53)+'Gasto Fijos y Variables'!AM23+'Gasto Fijos y Variables'!AM43 -> 3703.5817 | N13: =('Costes produción y ventas'!E4*'Costes produción y ventas'!Q21)+('Costes produción y ventas'!E5*'Costes produción y ventas'!Q29)+('Costes produción y ventas'!E6*'Costes produción y ventas'!Q37)+('Costes produción y ventas'!E7*'Costes produción y ventas'!Q45)+('Costes produción y ventas'!E8*'Costes produción y ventas'!Q53)+'Gasto Fijos y Variables'!AQ23+'Gasto Fijos y Variables'!AQ43 -> 3782.2317 | O13: =('Costes produción y ventas'!E4*'Costes produción y ventas'!R21)+('Costes produción y ventas'!E5*'Costes produción y ventas'!R29)+('Costes produción y ventas'!E6*'Costes produción y ventas'!R37)+('Costes produción y ventas'!E7*'Costes produción y ventas'!R45)+('Costes produción y ventas'!E8*'Costes produción y ventas'!R53)+'Gasto Fijos y Variables'!AU23+'Gasto Fijos y Variables'!AU43 -> 3260.1167 | P13: =('Costes produción y ventas'!E4*'Costes produción y ventas'!S21)+('Costes produción y ventas'!E5*'Costes produción y ventas'!S29)+('Costes produción y ventas'!E6*'Costes produción y ventas'!S37)+('Costes produción y ventas'!E7*'Costes produción y ventas'!S45)+('Costes produción y ventas'!E8*'Costes produción y ventas'!S53)+'Gasto Fijos y Variables'!AY23+'Gasto Fijos y Variables'!AY43 -> 1361.25
B14: Pago IVA a Hacienda | H14: ='Liquidación de IVA'!C9+'Liquidación de IVA'!D9+'Liquidación de IVA'!E9 -> -20061.3 | K14: ='Liquidación de IVA'!C15+'Liquidación de IVA'!D15+'Liquidación de IVA'!E15 -> 172.2 | N14: ='Liquidación de IVA'!C21+'Liquidación de IVA'!D21+'Liquidación de IVA'!E21 -> 1855.42 | P14: 0
B15: Devolución capital préstamos
B16: Pago de Intereses | E16: =('Necesidades de finaciación'!$F$16*'Necesidades de finaciación'!$H$16+'Necesidades de finaciación'!$F$17*'Necesidades de finaciación'!$H$17+'Necesidades de finaciación'!$F$18*'Necesidades de finaciación'!$H$18+'Necesidades de finaciación'!$F$24*'Necesidades de finaciación'!$H$24)/12 -> 1050 | F16: =('Necesidades de finaciación'!$F$16*'Necesidades de finaciación'!$H$16+'Necesidades de finaciación'!$F$17*'Necesidades de finaciación'!$H$17+'Necesidades de finaciación'!$F$18*'Necesidades de finaciación'!$H$18+'Necesidades de finaciación'!$F$24*'Necesidades de finaciación'!$H$24)/12 -> 1050 | G16: =('Necesidades de finaciación'!$F$16*'Necesidades de finaciación'!$H$16+'Necesidades de finaciación'!$F$17*'Necesidades de finaciación'!$H$17+'Necesidades de finaciación'!$F$18*'Necesidades de finaciación'!$H$18+'Necesidades de finaciación'!$F$24*'Necesidades de finaciación'!$H$24)/12 -> 1050 | H16: =('Necesidades de finaciación'!$F$16*'Necesidades de finaciación'!$H$16+'Necesidades de finaciación'!$F$17*'Necesidades de finaciación'!$H$17+'Necesidades de finaciación'!$F$18*'Necesidades de finaciación'!$H$18+'Necesidades de finaciación'!$F$24*'Necesidades de finaciación'!$H$24)/12 -> 1050 | I16: =('Necesidades de finaciación'!$F$16*'Necesidades de finaciación'!$H$16+'Necesidades de finaciación'!$F$17*'Necesidades de finaciación'!$H$17+'Necesidades de finaciación'!$F$18*'Necesidades de finaciación'!$H$18+'Necesidades de finaciación'!$F$24*'Necesidades de finaciación'!$H$24)/12 -> 1050 | J16: =('Necesidades de finaciación'!$F$16*'Necesidades de finaciación'!$H$16+'Necesidades de finaciación'!$F$17*'Necesidades de finaciación'!$H$17+'Necesidades de finaciación'!$F$18*'Necesidades de finaciación'!$H$18+'Necesidades de finaciación'!$F$24*'Necesidades de finaciación'!$H$24)/12 -> 1050 | K16: =('Necesidades de finaciación'!$F$16*'Necesidades de finaciación'!$H$16+'Necesidades de finaciación'!$F$17*'Necesidades de finaciación'!$H$17+'Necesidades de finaciación'!$F$18*'Necesidades de finaciación'!$H$18+'Necesidades de finaciación'!$F$24*'Necesidades de finaciación'!$H$24)/12 -> 1050 | L16: =('Necesidades de finaciación'!$F$16*'Necesidades de finaciación'!$H$16+'Necesidades de finaciación'!$F$17*'Necesidades de finaciación'!$H$17+'Necesidades de finaciación'!$F$18*'Necesidades de finaciación'!$H$18+'Necesidades de finaciación'!$F$24*'Necesidades de finaciación'!$H$24)/12 -> 1050 | ... P16: =('Necesidades de finaciación'!$F$16*'Necesidades de finaciación'!$H$16+'Necesidades de finaciación'!$F$17*'Necesidades de finaciación'!$H$17+'Necesidades de finaciación'!$F$18*'Necesidades de finaciación'!$H$18+'Necesidades de finaciación'!$F$24*'Necesidades de finaciación'!$H$24)/12 -> 1050
B17: Pago de Inversiones | D17: ='Pago de Inversiones'!E25 -> 0 | E17: ='Pago de Inversiones'!G25 -> 0 | F17: ='Pago de Inversiones'!I25 -> 0 | G17: ='Pago de Inversiones'!K25 -> 0 | H17: ='Pago de Inversiones'!M25 -> 0 | I17: ='Pago de Inversiones'!O25 -> 0 | J17: ='Pago de Inversiones'!Q25 -> 0 | K17: ='Pago de Inversiones'!S25 -> 0 | L17: ='Pago de Inversiones'!U25 -> 0 | M17: ='Pago de Inversiones'!W25 -> 0 | N17: ='Pago de Inversiones'!Y25 -> 0 | O17: ='Pago de Inversiones'!AA25 -> 0 | P17: ='Pago de Inversiones'!AC25 -> 0
B18: Total de Pagos | D18: =D16+D17 -> 0 | E18: =SUM(E12:E17) -> 5522.1667 | F18: =SUM(F12:F17) -> 5522.1667 | G18: =SUM(G12:G17) -> 5679.4667 | H18: =SUM(H12:H17) -> -14121.683 | I18: =SUM(I12:I17) -> 6018.2667 | J18: =SUM(J12:J17) -> 9493.25 | K18: =SUM(K12:K17) -> 10228.1 | L18: =SUM(L12:L17) -> 10608.265 | ... P18: =SUM(P12:P17) -> 6611.25
B19: Flujo de Caja Neto | D19: =D11-D18 -> 180000 | E19: =E11-E18 -> -5522.1667 | F19: =F11-F18 -> -5522.1667 | G19: =G11-G18 -> -5074.4667 | H19: =H11-H18 -> 15634.183 | I19: =I11-I18 -> -4203.2667 | J19: =J11-J18 -> -5560.75 | K19: =K11-K18 -> -4541.1 | ... P19: =P11-P18 -> -1468.75
B20: Poliza de credito | D20: 0 | Q20: 0
B21: Saldo Final de Tesorería | D21: =D19+D20 -> 180000 | E21: =D21+E19+E20 -> 174477.83 | F21: =E21+F19+F20 -> 168955.67 | G21: =F21+G19+G20 -> 163881.2 | H21: =G21+H19+H20 -> 179515.38 | I21: =H21+I19+I20 -> 175312.12 | J21: =I21+J19+J20 -> 169751.37 | K21: =J21+K19+K20 -> 165210.27 | L21: =K21+L19+L20 -> 162003.17 | ... P21: =O21+P19+P20 -> 150415.73
C23: Totales | F23: €
C24: Tesorería Inicio de Año | F24: =D21 -> 180000
C25: Necesidades de Financiación a C/P | F25: =P21 -> 150415.73
C26: Tesorería Final de Año | F26: =F25-F24 -> -29584.265

Sheet Cuenta de Resultados Mensual
B3: Cuenta de Resultados Mensual
C5: MES 1 | D5: MES 2 | E5: MES 3 | F5: MES 4 | G5: MES 5 | H5: MES 6 | I5: MES 7 | J5: MES 8 | K5: MES 9 | L5: MES 10 | M5: MES 11 | N5: MES 12 | O5: TOTAL
B6: Ingresos de Explotación | C6: ='Costes produción y ventas'!H23+'Costes produción y ventas'!H31+'Costes produción y ventas'!H39+'Costes produción y ventas'!H47+'Costes produción y ventas'!H55+'Flujo de Caja'!E7 -> 0 | D6: ='Costes produción y ventas'!I23+'Costes produción y ventas'!I31+'Costes produción y ventas'!I39+'Costes produción y ventas'!I47+'Costes produción y ventas'!I55+'Flujo de Caja'!F7 -> 0 | E6: ='Costes produción y ventas'!J23+'Costes produción y ventas'!J31+'Costes produción y ventas'!J39+'Costes produción y ventas'!J47+'Costes produción y ventas'!J55+'Flujo de Caja'!G7 -> 500 | F6: ='Costes produción y ventas'!K23+'Costes produción y ventas'!K31+'Costes produción y ventas'!K39+'Costes produción y ventas'!K47+'Costes produción y ventas'!K55+'Flujo de Caja'!H7 -> 1250 | G6: ='Costes produción y ventas'!L23+'Costes produción y ventas'!L31+'Costes produción y ventas'!L39+'Costes produción y ventas'!L47+'Costes produción y ventas'!L55+'Flujo de Caja'!I7 -> 1500 | H6: ='Costes produción y ventas'!M23+'Costes produción y ventas'!M31+'Costes produción y ventas'!M39+'Costes produción y ventas'!M47+'Costes produción y ventas'!M55+'Flujo de Caja'!J7 -> 3250 | I6: ='Costes produción y ventas'!N23+'Costes produción y ventas'!N31+'Costes produción y ventas'!N39+'Costes produción y ventas'!N47+'Costes produción y ventas'!N55+'Flujo de Caja'!K7 -> 4700 | J6: ='Costes produción y ventas'!O23+'Costes produción y ventas'!O31+'Costes produción y ventas'!O39+'Costes produción y ventas'!O47+'Costes produción y ventas'!O55+'Flujo de Caja'!L7 -> 6116.6667 | ... N6: ='Costes produción y ventas'!S23+'Costes produción y ventas'!S31+'Costes produción y ventas'!S39+'Costes produción y ventas'!S47+'Costes produción y ventas'!S55+'Flujo de Caja'!P7 -> 4250 | O6: =SUM(C6:N6) -> 39500
B7: Gastos de Explotación | C7: ='Costes produción y ventas'!H24+'Costes produción y ventas'!H32+'Costes produción y ventas'!H40+'Costes produción y ventas'!H48+'Costes produción y ventas'!H56 -> 0 | D7: ='Costes produción y ventas'!I24+'Costes produción y ventas'!I32+'Costes produción y ventas'!I40+'Costes produción y ventas'!I48+'Costes produción y ventas'!I56 -> 0 | E7: ='Costes produción y ventas'!J24+'Costes produción y ventas'!J32+'Costes produción y ventas'!J40+'Costes produción y ventas'!J48+'Costes produción y ventas'!J56 -> 130 | F7: ='Costes produción y ventas'!K24+'Costes produción y ventas'!K32+'Costes produción y ventas'!K40+'Costes produción y ventas'!K48+'Costes produción y ventas'!K56 -> 345 | G7: ='Costes produción y ventas'!L24+'Costes produción y ventas'!L32+'Costes produción y ventas'!L40+'Costes produción y ventas'!L48+'Costes produción y ventas'!L56 -> 410 | H7: ='Costes produción y ventas'!M24+'Costes produción y ventas'!M32+'Costes produción y ventas'!M40+'Costes produción y ventas'!M48+'Costes produción y ventas'!M56 -> 775 | I7: ='Costes produción y ventas'!N24+'Costes produción y ventas'!N32+'Costes produción y ventas'!N40+'Costes produción y ventas'!N48+'Costes produción y ventas'!N56 -> 1240 | J7: ='Costes produción y ventas'!O24+'Costes produción y ventas'!O32+'Costes produción y ventas'!O40+'Costes produción y ventas'!O48+'Costes produción y ventas'!O56 -> 1696.5 | ... N7: ='Costes produción y ventas'!S24+'Costes produción y ventas'!S32+'Costes produción y ventas'!S40+'Costes produción y ventas'!S48+'Costes produción y ventas'!S56 -> 1125 | O7: 10696
B8: Margen Bruto | C8: =C6-C7 -> 0 | D8: =D6-D7 -> 0 | E8: =E6-E7 -> 370 | F8: =F6-F7 -> 905 | G8: =G6-G7 -> 1090 | H8: =H6-H7 -> 2475 | I8: =I6-I7 -> 3460 | J8: =J6-J7 -> 4420.1667 | ... O8: =O6-O7 -> 28804
B9: Gastos de personal | C9: ='Gastos de Personal'!C32 -> 2900 | D9: ='Gastos de Personal'!D32 -> 2900 | E9: ='Gastos de Personal'!E32 -> 2900 | F9: ='Gastos de Personal'!F32 -> 2900 | G9: ='Gastos de Personal'!G32 -> 2900 | H9: ='Gastos de Personal'!H32 -> 5933.3333 | I9: ='Gastos de Personal'!I32 -> 5933.3333 | J9: ='Gastos de Personal'!J32 -> 5933.3333 | ... N9: ='Gastos de Personal'!N32 -> 4200 | O9: =SUM(C9:N9) -> 52566.667
B10: Gastos Fijos | C10: ='Gasto Fijos y Variables'!D23 -> 1083.3333 | D10: ='Gasto Fijos y Variables'!H23 -> 1083.3333 | E10: ='Gasto Fijos y Variables'!L23 -> 1083.3333 | F10: ='Gasto Fijos y Variables'!P23 -> 1083.3333 | G10: ='Gasto Fijos y Variables'!T23 -> 1083.3333 | H10: ='Gasto Fijos y Variables'!X23 -> 1083.3333 | I10: ='Gasto Fijos y Variables'!AB23 -> 1083.3333 | J10: ='Gasto Fijos y Variables'!AF23 -> 1083.3333 | K10: ='Gasto Fijos y Variables'!AJ23 -> 1083.3333 | L10: ='Gasto Fijos y Variables'!AN23 -> 1083.3333 | M10: ='Gasto Fijos y Variables'!AR23 -> 1083.3333 | N10: ='Gasto Fijos y Variables'!AV23 -> 0 | O10: =SUM(C10:N10) -> 11916.667
B11: Gastos Variables | C11: ='Gasto Fijos y Variables'!D43 -> 233.33333 | D11: ='Gasto Fijos y Variables'!H43 -> 233.33333 | E11: ='Gasto Fijos y Variables'!L43 -> 233.33333 | F11: ='Gasto Fijos y Variables'!P43 -> 233.33333 | G11: ='Gasto Fijos y Variables'!T43 -> 233.33333 | H11: ='Gasto Fijos y Variables'!X43 -> 233.33333 | I11: ='Gasto Fijos y Variables'!AB43 -> 233.33333 | J11: ='Gasto Fijos y Variables'!AF43 -> 233.33333 | K11: ='Gasto Fijos y Variables'!AJ43 -> 233.33333 | L11: ='Gasto Fijos y Variables'!AN43 -> 233.33333 | M11: ='Gasto Fijos y Variables'!AR43 -> 233.33333 | N11: ='Gasto Fijos y Variables'!AV43 -> 0 | O11: =SUM(C11:N11) -> 2566.6667
B12: Amortizaciones | C12: =('Amortización Contable'!F12+'Amortización Contable'!F24)/12 -> 978.83933 | D12: =('Amortización Contable'!F12+'Amortización Contable'!F24)/12 -> 978.83933 | E12: =('Amortización Contable'!F12+'Amortización Contable'!F24)/12 -> 978.83933 | F12: =('Amortización Contable'!F12+'Amortización Contable'!F24)/12 -> 978.83933 | G12: =('Amortización Contable'!F12+'Amortización Contable'!F24)/12 -> 978.83933 | H12: =('Amortización Contable'!F12+'Amortización Contable'!F24)/12 -> 978.83933 | I12: =('Amortización Contable'!F12+'Amortización Contable'!F24)/12 -> 978.83933 | J12: =('Amortización Contable'!F12+'Amortización Contable'!F24)/12 -> 978.83933 | K12: =('Amortización Contable'!F12+'Amortización Contable'!F24)/12 -> 978.83933 | L12: =('Amortización Contable'!F12+'Amortización Contable'!F24)/12 -> 978.83933 | M12: =('Amortización Contable'!F12+'Amortización Contable'!F24)/12 -> 978.83933 | N12: =('Amortización Contable'!F12+'Amortización Contable'!F24)/12 -> 978.83933 | O12: =SUM(C12:N12) -> 11746.072
B13: Total Gastos | C13: =SUM(C9:C12) -> 5195.506 | D13: =SUM(D9:D12) -> 5195.506 | E13: =SUM(E9:E12) -> 5195.506 | F13: =SUM(F9:F12) -> 5195.506 | G13: =SUM(G9:G12) -> 5195.506 | H13: =SUM(H9:H12) -> 8228.8393 | I13: =SUM(I9:I12) -> 8228.8393 | J13: =SUM(J9:J12) -> 8228.8393 | ... O13: =SUM(O9:O12) -> 78796.072
B14: Beneficios antes de impuestos e intereses (resultado de explotación) | C14: =(C8-C13) -> -5195.506 | D14: =(D8-D13) -> -5195.506 | E14: =(E8-E13) -> -4825.506 | F14: =(F8-F13) -> -4290.506 | G14: =(G8-G13) -> -4105.506 | H14: =(H8-H13) -> -5753.8393 | I14: =(I8-I13) -> -4768.8393 | J14: =(J8-J13) -> -3808.6727 | ... N14: =(N8-N13) -> -2053.8393 | O14: =O8-O13 -> -49992.072
B15: Gastos financieros | C15: =('Necesidades de finaciación'!$F$16*'Necesidades de finaciación'!$H$16+'Necesidades de finaciación'!$F$17*'Necesidades de finaciación'!$H$17+'Necesidades de finaciación'!$F$18*'Necesidades de finaciación'!$H$18+'Necesidades de finaciación'!$F$24*'Necesidades de finaciación'!$H$24)/12 -> 1050 | D15: =('Necesidades de finaciación'!$F$16*'Necesidades de finaciación'!$H$16+'Necesidades de finaciación'!$F$17*'Necesidades de finaciación'!$H$17+'Necesidades de finaciación'!$F$18*'Necesidades de finaciación'!$H$18+'Necesidades de finaciación'!$F$24*'Necesidades de finaciación'!$H$24)/12 -> 1050 | E15: =('Necesidades de finaciación'!$F$16*'Necesidades de finaciación'!$H$16+'Necesidades de finaciación'!$F$17*'Necesidades de finaciación'!$H$17+'Necesidades de finaciación'!$F$18*'Necesidades de finaciación'!$H$18+'Necesidades de finaciación'!$F$24*'Necesidades de finaciación'!$H$24)/12 -> 1050 | F15: =('Necesidades de finaciación'!$F$16*'Necesidades de finaciación'!$H$16+'Necesidades de finaciación'!$F$17*'Necesidades de finaciación'!$H$17+'Necesidades de finaciación'!$F$18*'Necesidades de finaciación'!$H$18+'Necesidades de finaciación'!$F$24*'Necesidades de finaciación'!$H$24)/12 -> 1050 | G15: =('Necesidades de finaciación'!$F$16*'Necesidades de finaciación'!$H$16+'Necesidades de finaciación'!$F$17*'Necesidades de finaciación'!$H$17+'Necesidades de finaciación'!$F$18*'Necesidades de finaciación'!$H$18+'Necesidades de finaciación'!$F$24*'Necesidades de finaciación'!$H$24)/12 -> 1050 | H15: =('Necesidades de finaciación'!$F$16*'Necesidades de finaciación'!$H$16+'Necesidades de finaciación'!$F$17*'Necesidades de finaciación'!$H$17+'Necesidades de finaciación'!$F$18*'Necesidades de finaciación'!$H$18+'Necesidades de finaciación'!$F$24*'Necesidades de finaciación'!$H$24)/12 -> 1050 | I15: =('Necesidades de finaciación'!$F$16*'Necesidades de finaciación'!$H$16+'Necesidades de finaciación'!$F$17*'Necesidades de finaciación'!$H$17+'Necesidades de finaciación'!$F$18*'Necesidades de finaciación'!$H$18+'Necesidades de finaciación'!$F$24*'Necesidades de finaciación'!$H$24)/12 -> 1050 | J15: =('Necesidades de finaciación'!$F$16*'Necesidades de finaciación'!$H$16+'Necesidades de finaciación'!$F$17*'Necesidades de finaciación'!$H$17+'Necesidades de finaciación'!$F$18*'Necesidades de finaciación'!$H$18+'Necesidades de finaciación'!$F$24*'Necesidades de finaciación'!$H$24)/12 -> 1050 | ... N15: =('Necesidades de finaciación'!$F$16*'Necesidades de finaciación'!$H$16+'Necesidades de finaciación'!$F$17*'Necesidades de finaciación'!$H$17+'Necesidades de finaciación'!$F$18*'Necesidades de finaciación'!$H$18+'Necesidades de finaciación'!$F$24*'Necesidades de finaciación'!$H$24)/12 -> 1050 | O15: =SUM(C15:N15) -> 12600
B16: Comisiones bancarias | O16: =SUM(C16:N16) -> 0
B17: Beneficios antes de impuestos | C17: =(C14-C15-C16) -> -6245.506 | D17: =(D14-D15-D16) -> -6245.506 | E17: =(E14-E15-E16) -> -5875.506 | F17: =(F14-F15-F16) -> -5340.506 | G17: =(G14-G15-G16) -> -5155.506 | H17: =(H14-H15-H16) -> -6803.8393 | I17: =(I14-I15-I16) -> -5818.8393 | J17: =(J14-J15-J16) -> -4858.6727 | ... N17: =(N14-N15-N16) -> -3103.8393 | O17: =O14-O15-O16 -> -62592.072
B18: Impuestos de ejecicio corrientes (Tasas municipales, IAE, IBI…) | O18: =SUM(C18:N18) -> 0
B19: SEGUIMIENTO DE RESULTADO | C19: =(C17-C18) -> -6245.506 | D19: =(D17-D18) -> -6245.506 | E19: =(E17-E18) -> -5875.506 | F19: =(F17-F18) -> -5340.506 | G19: =(G17-G18) -> -5155.506 | H19: =(H17-H18) -> -6803.8393 | I19: =(I17-I18) -> -5818.8393 | J19: =(J17-J18) -> -4858.6727 | ... N19: =(N17-N18) -> -3103.8393 | O19: -82362.67

Sheet Balance
B2: Balance
B4: ACTIVO | C4: =C5+C28 -> 247266.33 | E4: PATRIMONIO NETO Y PASIVO | F4: =F5+F9+F14 -> 247266.33
B5: Activo no corriente | C5: =C6+C19 -> 80714.648 | E5: Patrimonio Neto | F5: =F6+F7+F8 -> 49232.648
B6: Inmovilizado material | C6: =SUM(C7:C18) -> 9000 | E6: Capital | F6: ='Inversión Inicial'!H6+'Inversión Inicial'!H7+'Inversión Inicial'!H8+'Inversión Inicial'!H9+'Inversión Inicial'!H10+'Inversión Inicial'!H11+'Inversión Inicial'!H12+'Inversión Inicial'!H13+'Inversión Inicial'!H14+'Inversión Inicial'!H15+'Inversión Inicial'!H16+'Inversión Inicial'!H19+'Inversión Inicial'!H20+'Inversión Inicial'!H21+'Inversión Inicial'!H22+'Inversión Inicial'!H23+'Inversión Inicial'!H24+'Inversión Inicial'!H25+'Inversión Inicial'!H28+'Necesidades de finaciación'!F9 -> 0
B7: Adquisición del terreno | C7: ='Inversión Inicial'!C6+'Inversión Inicial'!E6+'Inversión Inicial'!H6 -> 0 | E7: Resultado del Ejercicio | F7: ='Cuenta de Resultados Mensual'!O19 -> -82362.67
B8: Edificios y Construcciones | C8: ='Amortización Contable'!C15 -> 0 | E8: Financiación externa proforma condicionada (no caja propia; requiere desembolso) | F8: =C37-F6-F7-F9-F14 -> 131595.32
B9: Instalaciones | C9: ='Amortización Contable'!C16 -> 0 | E9: Pasivo no corriente | F9: =F10+F11+F12+F13 -> 168033.68
B10: Maquinaria | C10: ='Amortización Contable'!C17 -> 0 | E10: Préstamos bancarios a largo | F10: =('Necesidades de finaciación'!F17-SUM('Flujo de Caja'!E14:P14)*IF('Necesidades de finaciación'!F17+'Necesidades de finaciación'!F18=0,0,'Necesidades de finaciación'!F17/('Necesidades de finaciación'!F17+'Necesidades de finaciación'!F18)))-MIN(('Necesidades de finaciación'!F17-SUM('Flujo de Caja'!E15:P15)*IF('Necesidades de finaciación'!F17+'Necesidades de finaciación'!F18=0,0,'Necesidades de finaciación'!F17/('Necesidades de finaciación'!F17+'Necesidades de finaciación'!F18))),IF('Necesidades de finaciación'!G17=0,0,'Necesidades de finaciación'!F17/('Necesidades de finaciación'!G17-1))) -> 168033.68
B11: Equipamiento | C11: ='Amortización Contable'!C18 -> 0 | E11: Microcréditos a largo | F11: =('Necesidades de finaciación'!F18-SUM('Flujo de Caja'!E15:P15)*(1-IF('Necesidades de finaciación'!F17+'Necesidades de finaciación'!F18=0,0,'Necesidades de finaciación'!F17/('Necesidades de finaciación'!F17+'Necesidades de finaciación'!F18))))-MIN(('Necesidades de finaciación'!F18-SUM('Flujo de Caja'!E15:P15)*(1-IF('Necesidades de finaciación'!F17+'Necesidades de finaciación'!F18=0,0,'Necesidades de finaciación'!F17/('Necesidades de finaciación'!F17+'Necesidades de finaciación'!F18)))),IF('Necesidades de finaciación'!G18=0,0,'Necesidades de finaciación'!F18/'Necesidades de finaciación'!G18)) -> 0
B12: Mobiliario | C12: ='Amortización Contable'!C19 -> 0 | E12: Otras deudas a largo plazo | F12: ='Necesidades de finaciación'!F16 -> 0
B13: Utillaje | C13: ='Amortización Contable'!C20 -> 0 | E13: Acreedores por arrendamiento financiero a Largo Plazo | F13: 0
B14: Vehículos de transporte | C14: ='Amortización Contable'!C21 -> 0 | E14: Pasivo Corriente | F14: =F15+F16+F17+F18+F19+F20+F21+F22+F23 -> 30000
B15: Equipos informáticos | C15: ='Amortización Contable'!C22 -> 0 | E15: Póliza de Crédito | F15: ='Flujo de Caja'!Q20 -> 0
B16: Otros (proyectos técnicos...) | C16: ='Amortización Contable'!C23 -> 10000 | E16: Proveedores varios | F16: ='Necesidades de finaciación'!F24 -> 0
B17: Fianza | C17: ='Inversión Inicial'!C16+'Inversión Inicial'!E16+'Inversión Inicial'!H16 -> 0 | E17: Préstamo Bancario a corto plazo | F17: =MIN(('Necesidades de finaciación'!F17-SUM('Flujo de Caja'!E15:P15)*IF('Necesidades de finaciación'!F17+'Necesidades de finaciación'!F18=0,0,'Necesidades de finaciación'!F17/('Necesidades de finaciación'!F17+'Necesidades de finaciación'!F18))),IF('Necesidades de finaciación'!G17=0,0,'Necesidades de finaciación'!F17/('Necesidades de finaciación'!G17-1))) -> 30000
B18: (-) Amortización acumulada del inmovilizado material | C18: =-('Amortización Contable'!F24) -> -1000 | E18: Microcréditos a largo | F18: =MIN(('Necesidades de finaciación'!F18-SUM('Flujo de Caja'!E15:P15)*(1-IF('Necesidades de finaciación'!F17+'Necesidades de finaciación'!F18=0,0,'Necesidades de finaciación'!F17/('Necesidades de finaciación'!F17+'Necesidades de finaciación'!F18)))),IF('Necesidades de finaciación'!G18=0,0,'Necesidades de finaciación'!F18/'Necesidades de finaciación'!G18)) -> 0
B19: Inmovilizado inmaterial | C19: =SUM(C20:C27) -> 71714.648 | E19: Hacienda Pública (acreedor por IVA) | F19: =MAX(0,'Liquidación de IVA'!I8+'Liquidación de IVA'!I9+'Liquidación de IVA'!I10+'Liquidación de IVA'!I11)-MAX(0,'Liquidación de IVA'!I8+'Liquidación de IVA'!I9+'Liquidación de IVA'!I10) -> 0
B20: Gastos de I+D | C20: ='Amortización Contable'!C5 -> 30000 | E20: Hacienda Pública (acreedor Impuesto de Sociedades) | F20: ='Cuenta de Resultados Mensual'!O18 -> 0
B21: Patentes, Modelos de Utilidad | C21: ='Amortización Contable'!C6 -> 0
B22: Aplicaciones informáticas | C22: ='Amortización Contable'!C7 -> 47250
B23: Derechos de traspaso, Concesiones administrativas, Tasas, Licencias... | C23: ='Amortización Contable'!C8 -> 0
B24: Marca, Nombre Comercial | C24: ='Amortización Contable'!C10 -> 210.72
B25: Otros (...) | C25: ='Amortización Contable'!C11 -> 5000
B26: Fondo de Comercio | C26: ='Amortización Contable'!C9 -> 0
B27: (-)Amortización acumulada del inmovilizado inmaterial | C27: =-('Amortización Contable'!F12) -> -10746.072
B28: Activo corriente | C28: =C29+C30+C32 -> 166551.68
B29: Existencias, materias primas... | C29: ='Inversión Inicial'!C28+'Inversión Inicial'!E28+'Inversión Inicial'!H28 -> 0
B30: Hacienda Pública (deudor por IVA) | C30: =MAX(0,-('Liquidación de IVA'!I8+'Liquidación de IVA'!I9+'Liquidación de IVA'!I10+'Liquidación de IVA'!I11)) -> 16135.945
B31: Clientes | C31: 0
B32: Tesorería | C32: ='Flujo de Caja'!P21 -> 150415.73
B35: NOTA: el balance proforma condicionado cierra matemáticamente; las partidas de financiación y documentación quedan sujetas a formalización, justificación y desembolso.
B37: TOTAL ACTIVO | C37: =C4 -> 247266.33
B38: TOTAL PASIVO | C38: =F4 -> 247266.33 | E38: TOTAL PATRIMONIO NETO Y PASIVO | F38: =F4 -> 247266.33
E39: CONTROL DE CIERRE | F39: =C37-F38 -> 0

Sheet Cuenta de Resultados Proyectada
A1: PIE PLUS 2026 · PLAN FINANCIERO OFICIAL · V5.6 PULIDO · ESCENARIO PROFORMA CONDICIONADO
A2: ADVERTENCIA: 180.000 € es financiación pendiente de formalización y desembolso; no es financiación concedida ni cobrada. Caja propia inicial: 0,00 €.
B3: Tipo impositivo sobre beneficios (editable) → (IRPF / Impuesto de sociedades) * | C3: 0.15
B4: % Crecimiento Anual (editable) → | D4: 0.02 | E4: 0.05 | F4: 0.07 | G4: 0.1
C5: Año 1 | D5: Año 2 | E5: Año 3 | F5: Año 4 | G5: Año 5
B6: Ingresos de Explotación | C6: ='Cuenta de Resultados Mensual'!O6 -> 39500 | D6: =C6*(1+D$4) -> 40290 | E6: =D6*(1+E$4) -> 42304.5 | F6: =E6*(1+F$4) -> 45265.815 | G6: =F6*(1+G$4) -> 49792.397
B7: Consumos | C7: ='Cuenta de Resultados Mensual'!O7 -> 10696 | D7: =C7*(1+D$4) -> 10909.92 | E7: =D7*(1+E$4) -> 11455.416 | F7: =E7*(1+F$4) -> 12257.295 | G7: =F7*(1+G$4) -> 13483.025
B8: Margen Bruto | C8: =C6-C7 -> 28804 | D8: =D6-D7 -> 29380.08 | E8: =E6-E7 -> 30849.084 | F8: =F6-F7 -> 33008.52 | G8: =G6-G7 -> 36309.372
B9: Margen Bruto sobre Ventas | C9: =C8/C6 -> 0.72921519 | D9: =D8/D6 -> 0.72921519 | E9: =E8/E6 -> 0.72921519 | F9: =F8/F6 -> 0.72921519 | G9: =G8/G6 -> 0.72921519
B10: Gastos de personal | C10: ='Cuenta de Resultados Mensual'!O9 -> 52566.667 | D10: =C10*(1+D$4) -> 53618 | E10: =D10*(1+E$4) -> 56298.9 | F10: =E10*(1+F$4) -> 60239.823 | G10: =F10*(1+G$4) -> 66263.805
B11: Gastos Variables | C11: ='Cuenta de Resultados Mensual'!O11 -> 2566.6667 | D11: =C11*(1+D$4) -> 2618 | E11: =D11*(1+E$4) -> 2748.9 | F11: =E11*(1+F$4) -> 2941.323 | G11: =F11*(1+G$4) -> 3235.4553
B12: Gastos Fijos | C12: ='Cuenta de Resultados Mensual'!O10 -> 11916.667 | D12: =C12*(1+D$4) -> 12155 | E12: =D12*(1+E$4) -> 12762.75 | F12: =E12*(1+F$4) -> 13656.142 | G12: =F12*(1+G$4) -> 15021.757
B13: Amortizaciones | C13: ='Cuenta de Resultados Mensual'!O12 -> 11746.072 | D13: =C13*(1+D$4) -> 11980.993 | E13: =D13*(1+E$4) -> 12580.043 | F13: =E13*(1+F$4) -> 13460.646 | G13: =F13*(1+G$4) -> 14806.711
B14: Total Gastos | C14: ='Cuenta de Resultados Mensual'!O13 -> 78796.072 | D14: =SUM(D10:D13) -> 80371.993 | E14: =SUM(E10:E13) -> 84390.593 | F14: =SUM(F10:F13) -> 90297.935 | G14: =SUM(G10:G13) -> 99327.728
B15: Beneficios antes de impuestos e intereses | C15: ='Cuenta de Resultados Mensual'!O14 -> -49992.072 | D15: =D8-D14 -> -50991.913 | E15: =E8-E14 -> -53541.509 | F15: =F8-F14 -> -57289.415 | G15: =F15*(1+G$4) -> -63018.356
B16: Gastos financieros | C16: ='Cuenta de Resultados Mensual'!O15 -> 12600 | D16: ='Necesidades de finaciación'!F17*'Necesidades de finaciación'!H17/12*(12-66/36) -> 10675 | E16: ='Necesidades de finaciación'!F17*'Necesidades de finaciación'!H17/12*(8-66/36) -> 6475 | F16: ='Necesidades de finaciación'!F17*'Necesidades de finaciación'!H17/12*(4-66/36) -> 2275 | G16: 0
B17: Beneficios antes de impuestos | C17: ='Cuenta de Resultados Mensual'!O17 -> -62592.072 | D17: =D15-D16 -> -61666.913 | E17: =E15-E16 -> -60016.509 | F17: =F15-F16 -> -59564.415 | G17: =G15-G16 -> -63018.356
A18: PUNTO DE EQUILIBRIO — OBJETIVO NO ALCANZADO EN AÑO 1
A19: Umbral operativo antes de intereses | B19: 143396.18 | C19: =C17-C18 -> -62592.072 | D19: =D17-D18 -> -61666.913 | E19: =E17-E18 -> -60016.509 | F19: =F17-F18 -> -59564.415 | G19: =G17-G18 -> -63018.356
A20: Umbral incluyendo intereses | B20: 152447.01
A21: Ingresos previstos Año 1 | B21: =C6 -> 39500 | C21: 0
A22: Estado | B22: No alcanzado; objetivo condicionado | C22: =C21*780000 -> 0
A23: F3 Invernadero 1 ha + hidroponía | B23: Referencia CAPEX | C23: =C21*1630000 -> 0
A24: F4 Agrovoltaica 1,3 MWp | B24: Referencia CAPEX | C24: =C21*2925000 -> 0
A25: PLANO C — CAPEX FÍSICO FUTURO CONDICIONADO (no activo en el escenario base) | B25: Referencia CAPEX | C25: =C21*760000 -> 0
A26: Estado de activación | B26: Referencia CAPEX | C26: 0
A27: F2 Geotermia + TRT | B27: Referencia CAPEX | C27: 780000
A28: F3 Invernadero 1 ha + hidroponía | B28: Referencia CAPEX | C28: 1630000
A29: F4 Agrovoltaica 1,3 MWp | B29: Referencia CAPEX | C29: 2925000
A30: BESS + F5 Datos soberanos | B30: Referencia CAPEX | C30: 760000
A31: Nota: el CAPEX físico se activa solo tras Gates y, si se activa, deberá incorporar financiación, amortización, carga financiera, permisos y evidencia.
